Workbook

Sheet Amortissement linéaire
B2: Amortissement Lineaire
B5: Détails de L'immobilisation
B7: Valeur du bien ** | D7: 25562.82 | E7: ** Doit être la valeur hors TVA du bien acheté
B8: Nombre d'années d'amortissement | D8: 5
B9: Date d'acquisition (jj/mm/aaa) | D9: 44743
B10: Date de début d'exercice* (jj/mm/aaaa) | D10: 44562 | E10: *Date complète de début d'exercice de l'année d'acquisition de l'immobilisation. Doit être avant la date d'acquisition de l'immobilisation
B11: Durée d'utilisation 1ère année | D11: =IF(OR(D9="",D10=""),"",(360-(D9-D10))) -> 179
B12: Durée d'utilisation dernière année | D12: =IF(OR(D9="",D10=""),"",360-D11) -> 181
B14: Tableau D'amortissement Linéaire
B16: Année | C16: Valeur comptable Début d'exercice | E16: Annuité d'amortissement | F16: Amortissements cumulés | G16: Valeur nette comptable en fin d'exercice
B17: =IF(OR(D8="",D7="",D11=""),"",1) -> 1 | C17: =IF(D7="","",D7) -> 25562.82 | E17: =IF(OR(B17="",D11=""),"",(D$7/D$8)*D11/360) -> 2542.0804 | F17: =E17 -> 2542.0804 | G17: =IF(B17="","",C17-E17) -> 23020.74
B18: =IF(B17="","",IF(B17+1>D$8+1,"",B17+1)) -> 2 | C18: =IF(B18="","",C17-E17) -> 23020.74 | E18: =IF(B18="","",IF(B18=D$8+1,(D$7/D$8)*(D$12/360),D$7/D$8)) -> 5112.564 | F18: =IF(B18="","",F17+E18) -> 7654.6444 | G18: =IF(B18="","",C18-E18) -> 17908.176
B19: =IF(B18="","",IF(B18+1>D$8+1,"",B18+1)) -> 3 | C19: =IF(B19="","",C18-E18) -> 17908.176 | E19: =IF(B19="","",IF(B19=D$8+1,(D$7/D$8)*(D$12/360),D$7/D$8)) -> 5112.564 | F19: =IF(B19="","",F18+E19) -> 12767.208 | G19: =IF(B19="","",C19-E19) -> 12795.612
B20: =IF(B19="","",IF(B19+1>D$8+1,"",B19+1)) -> 4 | C20: =IF(B20="","",C19-E19) -> 12795.612 | E20: =IF(B20="","",IF(B20=D$8+1,(D$7/D$8)*(D$12/360),D$7/D$8)) -> 5112.564 | F20: =IF(B20="","",F19+E20) -> 17879.772 | G20: =IF(B20="","",C20-E20) -> 7683.0476
B21: =IF(B20="","",IF(B20+1>D$8+1,"",B20+1)) -> 5 | C21: =IF(B21="","",C20-E20) -> 7683.0476 | E21: =IF(B21="","",IF(B21=D$8+1,(D$7/D$8)*(D$12/360),D$7/D$8)) -> 5112.564 | F21: =IF(B21="","",F20+E21) -> 22992.336 | G21: =IF(B21="","",C21-E21) -> 2570.4836
B22: =IF(B21="","",IF(B21+1>D$8+1,"",B21+1)) -> 6 | C22: =IF(B22="","",C21-E21) -> 2570.4836 | E22: =IF(B22="","",IF(B22=D$8+1,(D$7/D$8)*(D$12/360),D$7/D$8)) -> 2570.4836 | F22: =IF(B22="","",F21+E22) -> 25562.82 | G22: =IF(B22="","",C22-E22) -> -2.7284841e-12
B23: =IF(B22="","",IF(B22+1>D$8+1,"",B22+1)) | C23: =IF(B23="","",C22-E22) | E23: =IF(B23="","",IF(B23=D$8+1,(D$7/D$8)*(D$12/360),D$7/D$8)) | F23: =IF(B23="","",F22+E23) | G23: =IF(B23="","",C23-E23)
B24: =IF(B23="","",IF(B23+1>D$8+1,"",B23+1)) | C24: =IF(B24="","",C23-E23) | E24: =IF(B24="","",IF(B24=D$8+1,(D$7/D$8)*(D$12/360),D$7/D$8)) | F24: =IF(B24="","",F23+E24) | G24: =IF(B24="","",C24-E24)
B25: =IF(B24="","",IF(B24+1>D$8+1,"",B24+1)) | C25: =IF(B25="","",C24-E24) | E25: =IF(B25="","",IF(B25=D$8+1,(D$7/D$8)*(D$12/360),D$7/D$8)) | F25: =IF(B25="","",F24+E25) | G25: =IF(B25="","",C25-E25)
B26: =IF(B25="","",IF(B25+1>D$8+1,"",B25+1)) | C26: =IF(B26="","",C25-E25) | E26: =IF(B26="","",IF(B26=D$8+1,(D$7/D$8)*(D$12/360),D$7/D$8)) | F26: =IF(B26="","",F25+E26) | G26: =IF(B26="","",C26-E26)
B27: =IF(B26="","",IF(B26+1>D$8+1,"",B26+1)) | C27: =IF(B27="","",C26-E26) | E27: =IF(B27="","",IF(B27=D$8+1,(D$7/D$8)*(D$12/360),D$7/D$8)) | F27: =IF(B27="","",F26+E27) | G27: =IF(B27="","",C27-E27)

Sheet Amortissement dégressif
B2: Tableau D'amortissement Dégressif
J4: Janvier | K4: 12
B5: Détails de L'immobilisation | G5: Coeficient D'amortissement | J5: Février | K5: 11
J6: Mars | K6: 10
B7: Valeur du bien * | D7: 10000 | E7: * Doit être la valeur hors TVA du bien acheté | G7: Durée d'amortissement | H7: Coef à appliquer | J7: Avril | K7: 9
B8: Nb années d'amortissement | D8: 10 | G8: égale à 3 ou 4 ans | H8: 1.25 | J8: Mai | K8: 8
B9: Mois d'acquisiton | D9: Mars | G9: ègale à 5 ou 6 ans | H9: 1.75 | J9: Juin | K9: 7
B10: Coef à appliquer | D10: =IF(OR(D7="",D8=""),"",IF(D8<5,H8,IF(D8<7,H9,H10))) -> 2.25 | G10: Supérieure à 6 ans | H10: 2.25 | J10: Juillet | K10: 6
B11: Taux d'amortissement dégressif | D11: =IF(OR(D7="",D8=""),"",(1/D8)*D10) -> 0.225 | J11: Août | K11: 5
B12: Nb mois d'utilisation 1ère année | D12: =IF(D9="","",VLOOKUP(D9,J4:K15,2,0)) -> 10 | E12: Si votre année fiscale ne commence pas au 1er janvier, inscrivez manuellement le nombre de mois d'utilisation de votre immobilisation. | J12: Septembre | K12: 4
J13: Octobre | K13: 3
B14: Tableau D'amortissement Linéaire | J14: Novembre | K14: 2
J15: Décembre | K15: 1
B16: Année | C16: Valeur comptable Début d'exercice | E16: Annuité d'amortissement | F16: Amortissements cumulés | G16: Valeur nette comptable en fin d'exercice | H16: Taux linéaire | I16: Nombre d'années restantes
B17: =IF(OR(D8="",D7="",D9=""),"",1) -> 1 | C17: =IF(D7="","",D7) -> 10000 | E17: =IF(B17="","",(IF(D$11>H17,C17*D$11,C17*G17))*D12/12) -> 1875 | F17: =E17 -> 1875 | G17: =IF(B17="","",C17-E17) -> 8125 | H17: =IF(B17="","",1/I17) -> 0.1 | I17: =IF(D8="","",D8) -> 10
B18: =IF(OR(B17="",D$7=""),"",IF(B17+1>D$8,"",B17+1)) -> 2 | C18: =IF(B18="","",C17-E17) -> 8125 | E18: =IF(B18="","",IF(D$11>H18,C18*D$11,C18*H18)) -> 1828.125 | F18: =IF(B18="","",F17+E18) -> 3703.125 | G18: =IF(B18="","",C18-E18) -> 6296.875 | H18: =IF(B18="","",1/I18) -> 0.11111111 | I18: =IF(B18="","",I17-1) -> 9
B19: =IF(OR(B18="",D$7=""),"",IF(B18+1>D$8,"",B18+1)) -> 3 | C19: =IF(B19="","",C18-E18) -> 6296.875 | E19: =IF(B19="","",IF(D$11>H19,C19*D$11,C19*H19)) -> 1416.7969 | F19: =IF(B19="","",F18+E19) -> 5119.9219 | G19: =IF(B19="","",C19-E19) -> 4880.0781 | H19: =IF(B19="","",1/I19) -> 0.125 | I19: =IF(B19="","",I18-1) -> 8
B20: =IF(OR(B19="",D$7=""),"",IF(B19+1>D$8,"",B19+1)) -> 4 | C20: =IF(B20="","",C19-E19) -> 4880.0781 | E20: =IF(B20="","",IF(D$11>H20,C20*D$11,C20*H20)) -> 1098.0176 | F20: =IF(B20="","",F19+E20) -> 6217.9395 | G20: =IF(B20="","",C20-E20) -> 3782.0605 | H20: =IF(B20="","",1/I20) -> 0.14285714 | I20: =IF(B20="","",I19-1) -> 7
B21: =IF(OR(B20="",D$7=""),"",IF(B20+1>D$8,"",B20+1)) -> 5 | C21: =IF(B21="","",C20-E20) -> 3782.0605 | E21: =IF(B21="","",IF(D$11>H21,C21*D$11,C21*H21)) -> 850.96362 | F21: =IF(B21="","",F20+E21) -> 7068.9031 | G21: =IF(B21="","",C21-E21) -> 2931.0969 | H21: =IF(B21="","",1/I21) -> 0.16666667 | I21: =IF(B21="","",I20-1) -> 6
B22: =IF(OR(B21="",D$7=""),"",IF(B21+1>D$8,"",B21+1)) -> 6 | C22: =IF(B22="","",C21-E21) -> 2931.0969 | E22: =IF(B22="","",IF(D$11>H22,C22*D$11,C22*H22)) -> 659.49681 | F22: =IF(B22="","",F21+E22) -> 7728.3999 | G22: =IF(B22="","",C22-E22) -> 2271.6001 | H22: =IF(B22="","",1/I22) -> 0.2 | I22: =IF(B22="","",I21-1) -> 5
B23: =IF(OR(B22="",D$7=""),"",IF(B22+1>D$8,"",B22+1)) -> 7 | C23: =IF(B23="","",C22-E22) -> 2271.6001 | E23: =IF(B23="","",IF(D$11>H23,C23*D$11,C23*H23)) -> 567.90003 | F23: =IF(B23="","",F22+E23) -> 8296.2999 | G23: =IF(B23="","",C23-E23) -> 1703.7001 | H23: =IF(B23="","",1/I23) -> 0.25 | I23: =IF(B23="","",I22-1) -> 4
B24: =IF(OR(B23="",D$7=""),"",IF(B23+1>D$8,"",B23+1)) -> 8 | C24: =IF(B24="","",C23-E23) -> 1703.7001 | E24: =IF(B24="","",IF(D$11>H24,C24*D$11,C24*H24)) -> 567.90003 | F24: =IF(B24="","",F23+E24) -> 8864.1999 | G24: =IF(B24="","",C24-E24) -> 1135.8001 | H24: =IF(B24="","",1/I24) -> 0.33333333 | I24: =IF(B24="","",I23-1) -> 3
B25: =IF(OR(B24="",D$7=""),"",IF(B24+1>D$8,"",B24+1)) -> 9 | C25: =IF(B25="","",C24-E24) -> 1135.8001 | E25: =IF(B25="","",IF(D$11>H25,C25*D$11,C25*H25)) -> 567.90003 | F25: =IF(B25="","",F24+E25) -> 9432.1 | G25: =IF(B25="","",C25-E25) -> 567.90003 | H25: =IF(B25="","",1/I25) -> 0.5 | I25: =IF(B25="","",I24-1) -> 2
B26: =IF(OR(B25="",D$7=""),"",IF(B25+1>D$8,"",B25+1)) -> 10 | C26: =IF(B26="","",C25-E25) -> 567.90003 | E26: =IF(B26="","",IF(D$11>H26,C26*D$11,C26*H26)) -> 567.90003 | F26: =IF(B26="","",F25+E26) -> 10000 | G26: =IF(B26="","",C26-E26) -> 0 | H26: =IF(B26="","",1/I26) -> 1 | I26: =IF(B26="","",I25-1) -> 1

Sheet Saisie lin
B1: NEW LIFE Sàrl | E1: Amortissement Linéaire
B4: Détails de L'immobilisation | E4: VEHICULES MOTEUR
B6: Valeur du bien ** | D6: 25562.82 | E6: Car Avenue - Luxembourg
B7: Nombre d'années d'amortissement | D7: 5
B8: Date d'acquisition (jj/mm/aaa) | D8: 44743
B9: Date de début d'exercice * (jj/mm/aaaa) | D9: 44562
B10: Durée d'utilisation 1ère année | D10: =IF(OR(D8="",D9=""),"",(360-(D8-D9))) -> 179
B11: Durée d'utilisation dernière année | D11: =IF(OR(D8="",D9=""),"",360-D10) -> 181
B13: Tableau D'amortissement Linéaire
B15: Année | C15: Valeur comptable Début d'exercice | E15: Annuité d'amortissement | F15: Amortissements cumulés | G15: Valeur nette comptable en fin d'exercice
B16: =IF(OR(D7="",D6="",D10=""),"",1) -> 1 | C16: =IF(D6="","",D6) -> 25562.82 | E16: =IF(OR(B16="",D10=""),"",(D$6/D$7)*D10/360) -> 2542.0804 | F16: =E16 -> 2542.0804 | G16: =IF(B16="","",C16-E16) -> 23020.74
B17: =IF(B16="","",IF(B16+1>D$7+1,"",B16+1)) -> 2 | C17: =IF(B17="","",C16-E16) -> 23020.74 | E17: =IF(B17="","",IF(B17=D$7+1,(D$6/D$7)*(D$11/360),D$6/D$7)) -> 5112.564 | F17: =IF(B17="","",F16+E17) -> 7654.6444 | G17: =IF(B17="","",C17-E17) -> 17908.176
B18: =IF(B17="","",IF(B17+1>D$7+1,"",B17+1)) -> 3 | C18: =IF(B18="","",C17-E17) -> 17908.176 | E18: =IF(B18="","",IF(B18=D$7+1,(D$6/D$7)*(D$11/360),D$6/D$7)) -> 5112.564 | F18: =IF(B18="","",F17+E18) -> 12767.208 | G18: =IF(B18="","",C18-E18) -> 12795.612
B19: =IF(B18="","",IF(B18+1>D$7+1,"",B18+1)) -> 4 | C19: =IF(B19="","",C18-E18) -> 12795.612 | E19: =IF(B19="","",IF(B19=D$7+1,(D$6/D$7)*(D$11/360),D$6/D$7)) -> 5112.564 | F19: =IF(B19="","",F18+E19) -> 17879.772 | G19: =IF(B19="","",C19-E19) -> 7683.0476
B20: =IF(B19="","",IF(B19+1>D$7+1,"",B19+1)) -> 5 | C20: =IF(B20="","",C19-E19) -> 7683.0476 | E20: =IF(B20="","",IF(B20=D$7+1,(D$6/D$7)*(D$11/360),D$6/D$7)) -> 5112.564 | F20: =IF(B20="","",F19+E20) -> 22992.336 | G20: =IF(B20="","",C20-E20) -> 2570.4836
B21: =IF(B20="","",IF(B20+1>D$7+1,"",B20+1)) -> 6 | C21: =IF(B21="","",C20-E20) -> 2570.4836 | E21: =IF(B21="","",IF(B21=D$7+1,(D$6/D$7)*(D$11/360),D$6/D$7)) -> 2570.4836 | F21: =IF(B21="","",F20+E21) -> 25562.82 | G21: =IF(B21="","",C21-E21) -> -2.7284841e-12
B22: =IF(B21="","",IF(B21+1>D$7+1,"",B21+1)) | C22: =IF(B22="","",C21-E21) | E22: =IF(B22="","",IF(B22=D$7+1,(D$6/D$7)*(D$11/360),D$6/D$7)) | F22: =IF(B22="","",F21+E22) | G22: =IF(B22="","",C22-E22)
B23: =IF(B22="","",IF(B22+1>D$7+1,"",B22+1)) | C23: =IF(B23="","",C22-E22) | E23: =IF(B23="","",IF(B23=D$7+1,(D$6/D$7)*(D$11/360),D$6/D$7)) | F23: =IF(B23="","",F22+E23) | G23: =IF(B23="","",C23-E23)
B24: =IF(B23="","",IF(B23+1>D$7+1,"",B23+1)) | C24: =IF(B24="","",C23-E23) | E24: =IF(B24="","",IF(B24=D$7+1,(D$6/D$7)*(D$11/360),D$6/D$7)) | F24: =IF(B24="","",F23+E24) | G24: =IF(B24="","",C24-E24)
B25: =IF(B24="","",IF(B24+1>D$7+1,"",B24+1)) | C25: =IF(B25="","",C24-E24) | E25: =IF(B25="","",IF(B25=D$7+1,(D$6/D$7)*(D$11/360),D$6/D$7)) | F25: =IF(B25="","",F24+E25) | G25: =IF(B25="","",C25-E25)
B26: =IF(B25="","",IF(B25+1>D$7+1,"",B25+1)) | C26: =IF(B26="","",C25-E25) | E26: =IF(B26="","",IF(B26=D$7+1,(D$6/D$7)*(D$11/360),D$6/D$7)) | F26: =IF(B26="","",F25+E26) | G26: =IF(B26="","",C26-E26)
B28: * Date complète de début d'exercice de l'année d'acquisition de l'immobilisation. Doit être avant la date d'acquisition de l'immobilisation
B29: ** Doit être la valeur hors TVA du bien acheté

Sheet Amm auto
B1: NEW LIFE Sàrl | E1: Amortissement Linéaire
B4: Détails de L'immobilisation | E4: VEHICULES MOTEUR
B6: Valeur du bien ** | D6: =25562.81-8000 -> 17562.81 | E6: Car Avenue - Luxembourg
B7: Nombre d'années d'amortissement | D7: 5
B8: Date d'acquisition (jj/mm/aaa) | D8: 44742
B9: Date de début d'exercice * (jj/mm/aaaa) | D9: 44562
B10: Durée d'utilisation 1ère année | D10: =IF(OR(D8="",D9=""),"",(360-(D8-D9))) -> 180
B11: Durée d'utilisation dernière année | D11: =IF(OR(D8="",D9=""),"",360-D10) -> 180
B13: Tableau D'amortissement Linéaire
B15: Année | C15: Valeur comptable Début d'exercice | E15: Annuité d'amortissement | F15: Amortissements cumulés | G15: Valeur nette comptable en fin d'exercice
B16: =IF(OR(D7="",D6="",D10=""),"",1) -> 1 | C16: =IF(D6="","",D6) -> 17562.81 | E16: =IF(OR(B16="",D10=""),"",(D$6/D$7)*D10/360) -> 1756.281 | F16: =E16 -> 1756.281 | G16: =IF(B16="","",C16-E16) -> 15806.529
B17: =IF(B16="","",IF(B16+1>D$7+1,"",B16+1)) -> 2 | C17: =IF(B17="","",C16-E16) -> 15806.529 | E17: =IF(B17="","",IF(B17=D$7+1,(D$6/D$7)*(D$11/360),D$6/D$7)) -> 3512.562 | F17: =IF(B17="","",F16+E17) -> 5268.843 | G17: =IF(B17="","",C17-E17) -> 12293.967
B18: =IF(B17="","",IF(B17+1>D$7+1,"",B17+1)) -> 3 | C18: =IF(B18="","",C17-E17) -> 12293.967 | E18: =IF(B18="","",IF(B18=D$7+1,(D$6/D$7)*(D$11/360),D$6/D$7)) -> 3512.562 | F18: =IF(B18="","",F17+E18) -> 8781.405 | G18: =IF(B18="","",C18-E18) -> 8781.405
B19: =IF(B18="","",IF(B18+1>D$7+1,"",B18+1)) -> 4 | C19: =IF(B19="","",C18-E18) -> 8781.405 | E19: =IF(B19="","",IF(B19=D$7+1,(D$6/D$7)*(D$11/360),D$6/D$7)) -> 3512.562 | F19: =IF(B19="","",F18+E19) -> 12293.967 | G19: =IF(B19="","",C19-E19) -> 5268.843
B20: =IF(B19="","",IF(B19+1>D$7+1,"",B19+1)) -> 5 | C20: =IF(B20="","",C19-E19) -> 5268.843 | E20: =IF(B20="","",IF(B20=D$7+1,(D$6/D$7)*(D$11/360),D$6/D$7)) -> 3512.562 | F20: =IF(B20="","",F19+E20) -> 15806.529 | G20: =IF(B20="","",C20-E20) -> 1756.281
B21: =IF(B20="","",IF(B20+1>D$7+1,"",B20+1)) -> 6 | C21: =IF(B21="","",C20-E20) -> 1756.281 | E21: =IF(B21="","",IF(B21=D$7+1,(D$6/D$7)*(D$11/360),D$6/D$7)) -> 1756.281 | F21: =IF(B21="","",F20+E21) -> 17562.81 | G21: =IF(B21="","",C21-E21) -> 2.2737368e-13
B22: =IF(B21="","",IF(B21+1>D$7+1,"",B21+1)) | C22: =IF(B22="","",C21-E21) | E22: =IF(B22="","",IF(B22=D$7+1,(D$6/D$7)*(D$11/360),D$6/D$7)) | F22: =IF(B22="","",F21+E22) | G22: =IF(B22="","",C22-E22)
B23: =IF(B22="","",IF(B22+1>D$7+1,"",B22+1)) | C23: =IF(B23="","",C22-E22) | E23: =IF(B23="","",IF(B23=D$7+1,(D$6/D$7)*(D$11/360),D$6/D$7)) | F23: =IF(B23="","",F22+E23) | G23: =IF(B23="","",C23-E23)
B24: =IF(B23="","",IF(B23+1>D$7+1,"",B23+1)) | C24: =IF(B24="","",C23-E23) | E24: =IF(B24="","",IF(B24=D$7+1,(D$6/D$7)*(D$11/360),D$6/D$7)) | F24: =IF(B24="","",F23+E24) | G24: =IF(B24="","",C24-E24)
B25: =IF(B24="","",IF(B24+1>D$7+1,"",B24+1)) | C25: =IF(B25="","",C24-E24) | E25: =IF(B25="","",IF(B25=D$7+1,(D$6/D$7)*(D$11/360),D$6/D$7)) | F25: =IF(B25="","",F24+E25) | G25: =IF(B25="","",C25-E25)
B26: =IF(B25="","",IF(B25+1>D$7+1,"",B25+1)) | C26: =IF(B26="","",C25-E25) | E26: =IF(B26="","",IF(B26=D$7+1,(D$6/D$7)*(D$11/360),D$6/D$7)) | F26: =IF(B26="","",F25+E26) | G26: =IF(B26="","",C26-E26)
B28: * Date complète de début d'exercice de l'année d'acquisition de l'immobilisation. Doit être avant la date d'acquisition de l'immobilisation
B29: ** Doit être la valeur hors TVA du bien acheté

Sheet AMM A
C2: NEW LIFE Sàrl - Luxembourg | I2: 2025 | J2: Tableau d'Amortissement Linéaire | Q2: TOTALI
C4: SOFTWARE
B6: Nr | C6: Valeur du bien | D6: Nombre années amortissement | E6: Date acquisition | F6: Date début exercise | H6: Durée utilisation 1er année | I6: Durée utilisation dernière année | J6: Nr années | K6: Année | L6: Valeur comptable début d'exercise | M6: Annuité d'amortissement | N6: Amortissements cumulés | O6: Valeur nette comptable en fin d'exercice | Q6: Année | R6: Valeur comptable début d'exercise | S6: Annuité d'amortissement | T6: Amortissements cumulés | U6: Valeur nette comptable en fin d'exercice
B7: 1 | C7: 1007.2 | D7: 3 | E7: 45204 | F7: 44927 | G7: =YEAR(F7) -> 2023 | H7: =IF(OR(E7="",F7=""),"",(360-(E7-F7))) -> 83 | I7: =IF(OR(E7="",F7=""),"",360-H7) -> 277 | J7: =IF(OR(D7="",C7="",H7=""),"",1) -> 1 | K7: =IF(G7="","",G7) -> 2023 | L7: =IF(C7="","",C7) -> 1007.2 | M7: =IF(OR(J7="",H7=""),"",(C$7/D$7)*H7/360) -> 77.405185 | N7: =M7 -> 77.405185 | O7: =IF(J7="","",L7-M7) -> 929.79481 | Q7: 2022 | R7: =SUMIF($K$7:$K$61,Q7,$L$7:$L$61) -> 0 | S7: =SUMIF($K$7:$K$61,Q7,$M$7:$M$61) -> 0 | T7: =SUMIF($K$7:$K$61,Q7,$N$7:$N$61) -> 0 | U7: =SUMIF($K$7:$K$61,Q7,$O$7:$O$61) -> 0
C8: Pak Man - Hong Kong | E8: Bureautique | J8: =IF(J7="","",IF(J7+1>D$7+1,"",J7+1)) -> 2 | K8: =IF(J8="","",K7+1) -> 2024 | L8: =IF(J8="","",L7-M7) -> 929.79481 | M8: =IF(J8="","",IF(J8=D$7+1,(C$7/D$7)*(I$7/360),C$7/D$7)) -> 335.73333 | N8: =IF(J8="","",N7+M8) -> 413.13852 | O8: =IF(J8="","",L8-M8) -> 594.06148 | Q8: =Q7+1 -> 2023 | R8: =SUMIF($K$7:$K$61,Q8,$L$7:$L$61) -> 4391.65 | S8: =SUMIF($K$7:$K$61,Q8,$M$7:$M$61) -> 195.97162 | T8: =SUMIF($K$7:$K$61,Q8,$N$7:$N$61) -> 195.97162 | U8: =SUMIF($K$7:$K$61,Q8,$O$7:$O$61) -> 4195.6784
J9: =IF(J8="","",IF(J8+1>D$7+1,"",J8+1)) -> 3 | K9: =IF(J9="","",K8+1) -> 2025 | L9: =IF(J9="","",L8-M8) -> 594.06148 | M9: =IF(J9="","",IF(J9=D$7+1,(C$7/D$7)*(I$7/360),C$7/D$7)) -> 335.73333 | N9: =IF(J9="","",N8+M9) -> 748.87185 | O9: =IF(J9="","",L9-M9) -> 258.32815 | Q9: =Q8+1 -> 2024 | R9: =SUMIF($K$7:$K$61,Q9,$L$7:$L$61) -> 7198.9384 | S9: =SUMIF($K$7:$K$61,Q9,$M$7:$M$61) -> 2161.8632 | T9: =SUMIF($K$7:$K$61,Q9,$N$7:$N$61) -> 2357.8348 | U9: =SUMIF($K$7:$K$61,Q9,$O$7:$O$61) -> 5037.0752
J10: =IF(J9="","",IF(J9+1>D$7+1,"",J9+1)) -> 4 | K10: =IF(J10="","",K9+1) -> 2026 | L10: =IF(J10="","",L9-M9) -> 258.32815 | M10: =IF(J10="","",IF(J10=D$7+1,(C$7/D$7)*(I$7/360),C$7/D$7)) -> 258.32815 | N10: =IF(J10="","",N9+M10) -> 1007.2 | O10: =IF(J10="","",L10-M10) -> -5.6843419e-14 | Q10: =Q9+1 -> 2025 | R10: =SUMIF($K$7:$K$61,Q10,$L$7:$L$61) -> 5037.0752 | S10: =SUMIF($K$7:$K$61,Q10,$M$7:$M$61) -> 2464.97 | T10: =SUMIF($K$7:$K$61,Q10,$N$7:$N$61) -> 4822.8048 | U10: =SUMIF($K$7:$K$61,Q10,$O$7:$O$61) -> 2572.1052
J11: =IF(J10="","",IF(J10+1>D$7+1,"",J10+1)) | K11: =IF(J11="","",K10+1) | L11: =IF(J11="","",L10-M10) | M11: =IF(J11="","",IF(J11=D$7+1,(C$7/D$7)*(I$7/360),C$7/D$7)) | N11: =IF(J11="","",N10+M11) | O11: =IF(J11="","",L11-M11) | Q11: =Q10+1 -> 2026 | R11: =SUMIF($K$7:$K$61,Q11,$L$7:$L$61) -> 2572.1052 | S11: =SUMIF($K$7:$K$61,Q11,$M$7:$M$61) -> 2268.9984 | T11: =SUMIF($K$7:$K$61,Q11,$N$7:$N$61) -> 7091.8032 | U11: =SUMIF($K$7:$K$61,Q11,$O$7:$O$61) -> 303.1068
J12: =IF(J11="","",IF(J11+1>D$7+1,"",J11+1)) | K12: =IF(J12="","",K11+1) | L12: =IF(J12="","",L11-M11) | M12: =IF(J12="","",IF(J12=D$7+1,(C$7/D$7)*(I$7/360),C$7/D$7)) | N12: =IF(J12="","",N11+M12) | O12: =IF(J12="","",L12-M12) | Q12: =Q11+1 -> 2027 | R12: =SUMIF($K$7:$K$61,Q12,$L$7:$L$61) -> 303.1068 | S12: =SUMIF($K$7:$K$61,Q12,$M$7:$M$61) -> 303.1068 | T12: =SUMIF($K$7:$K$61,Q12,$N$7:$N$61) -> 3003.26 | U12: =SUMIF($K$7:$K$61,Q12,$O$7:$O$61) -> 1.7053026e-13
Q13: =Q12+1 -> 2028 | R13: =SUMIF($K$7:$K$61,Q13,$L$7:$L$61) -> 0 | S13: =SUMIF($K$7:$K$61,Q13,$M$7:$M$61) -> 0 | T13: =SUMIF($K$7:$K$61,Q13,$N$7:$N$61) -> 0 | U13: =SUMIF($K$7:$K$61,Q13,$O$7:$O$61) -> 0
B14: =B7+1 -> 2 | C14: 1200.77 | D14: 3 | E14: 45204 | F14: 44927 | G14: =YEAR(F14) -> 2023 | H14: =IF(OR(E14="",F14=""),"",(360-(E14-F14))) -> 83 | I14: =IF(OR(E14="",F14=""),"",360-H14) -> 277 | J14: =IF(OR(D14="",C14="",H14=""),"",1) -> 1 | K14: =IF(G14="","",G14) -> 2023 | L14: =IF(C14="","",C14) -> 1200.77 | M14: =IF(OR(J14="",H14=""),"",(C$14/D$14)*H14/360) -> 92.281398 | N14: =M14 -> 92.281398 | O14: =IF(J14="","",L14-M14) -> 1108.4886 | Q14: =Q13+1 -> 2029 | R14: =SUMIF($K$7:$K$61,Q14,$L$7:$L$61) -> 0 | S14: =SUMIF($K$7:$K$61,Q14,$M$7:$M$61) -> 0 | T14: =SUMIF($K$7:$K$61,Q14,$N$7:$N$61) -> 0 | U14: =SUMIF($K$7:$K$61,Q14,$O$7:$O$61) -> 0
C15: Pak Man - Hong Kong | E15: Bureautique | J15: =IF(J14="","",IF(J14+1>D$14+1,"",J14+1)) -> 2 | K15: =IF(J15="","",K14+1) -> 2024 | L15: =IF(J15="","",L14-M14) -> 1108.4886 | M15: =IF(J15="","",IF(J15=D$14+1,(C$14/D$14)*(I$14/360),C$14/D$14)) -> 400.25667 | N15: =IF(J15="","",N14+M15) -> 492.53806 | O15: =IF(J15="","",L15-M15) -> 708.23194 | Q15: =Q14+1 -> 2030 | R15: =SUMIF($K$7:$K$61,Q15,$L$7:$L$61) -> 0 | S15: =SUMIF($K$7:$K$61,Q15,$M$7:$M$61) -> 0 | T15: =SUMIF($K$7:$K$61,Q15,$N$7:$N$61) -> 0 | U15: =SUMIF($K$7:$K$61,Q15,$O$7:$O$61) -> 0
J16: =IF(J15="","",IF(J15+1>D$14+1,"",J15+1)) -> 3 | K16: =IF(J16="","",K15+1) -> 2025 | L16: =IF(J16="","",L15-M15) -> 708.23194 | M16: =IF(J16="","",IF(J16=D$14+1,(C$14/D$14)*(I$14/360),C$14/D$14)) -> 400.25667 | N16: =IF(J16="","",N15+M16) -> 892.79473 | O16: =IF(J16="","",L16-M16) -> 307.97527
J17: =IF(J16="","",IF(J16+1>D$14+1,"",J16+1)) -> 4 | K17: =IF(J17="","",K16+1) -> 2026 | L17: =IF(J17="","",L16-M16) -> 307.97527 | M17: =IF(J17="","",IF(J17=D$14+1,(C$14/D$14)*(I$14/360),C$14/D$14)) -> 307.97527 | N17: =IF(J17="","",N16+M17) -> 1200.77 | O17: =IF(J17="","",L17-M17) -> 0
J18: =IF(J17="","",IF(J17+1>D$14+1,"",J17+1)) | K18: =IF(J18="","",K17+1) | L18: =IF(J18="","",L17-M17) | M18: =IF(J18="","",IF(J18=D$14+1,(C$14/D$14)*(I$14/360),C$14/D$14)) | N18: =IF(J18="","",N17+M18) | O18: =IF(J18="","",L18-M18)
J19: =IF(J18="","",IF(J18+1>D$14+1,"",J18+1)) | K19: =IF(J19="","",K18+1) | L19: =IF(J19="","",L18-M18) | M19: =IF(J19="","",IF(J19=D$14+1,(C$14/D$14)*(I$14/360),C$14/D$14)) | N19: =IF(J19="","",N18+M19) | O19: =IF(J19="","",L19-M19)
B21: =B14+1 -> 3 | C21: 2183.68 | D21: 3 | E21: 45274 | F21: 44927 | G21: =YEAR(F21) -> 2023 | H21: =IF(OR(E21="",F21=""),"",(360-(E21-F21))) -> 13 | I21: =IF(OR(E21="",F21=""),"",360-H21) -> 347 | J21: =IF(OR(D21="",C21="",H21=""),"",1) -> 1 | K21: =IF(G21="","",G21) -> 2023 | L21: =IF(C21="","",C21) -> 2183.68 | M21: =IF(OR(J21="",H21=""),"",(C$21/D$21)*H21/360) -> 26.285037 | N21: =M21 -> 26.285037 | O21: =IF(J21="","",L21-M21) -> 2157.395
J22: =IF(J21="","",IF(J21+1>D$21+1,"",J21+1)) -> 2 | K22: =IF(J22="","",K21+1) -> 2024 | L22: =IF(J22="","",L21-M21) -> 2157.395 | M22: =IF(J22="","",IF(J22=D$21+1,(C$21/D$21)*(I$21/360),C$21/D$21)) -> 727.89333 | N22: =IF(J22="","",N21+M22) -> 754.17837 | O22: =IF(J22="","",L22-M22) -> 1429.5016
J23: =IF(J22="","",IF(J22+1>D$21+1,"",J22+1)) -> 3 | K23: =IF(J23="","",K22+1) -> 2025 | L23: =IF(J23="","",L22-M22) -> 1429.5016 | M23: =IF(J23="","",IF(J23=D$21+1,(C$21/D$21)*(I$21/360),C$21/D$21)) -> 727.89333 | N23: =IF(J23="","",N22+M23) -> 1482.0717 | O23: =IF(J23="","",L23-M23) -> 701.6083
J24: =IF(J23="","",IF(J23+1>D$21+1,"",J23+1)) -> 4 | K24: =IF(J24="","",K23+1) -> 2026 | L24: =IF(J24="","",L23-M23) -> 701.6083 | M24: =IF(J24="","",IF(J24=D$21+1,(C$21/D$21)*(I$21/360),C$21/D$21)) -> 701.6083 | N24: =IF(J24="","",N23+M24) -> 2183.68 | O24: =IF(J24="","",L24-M24) -> -2.2737368e-13
J25: =IF(J24="","",IF(J24+1>D$21+1,"",J24+1)) | K25: =IF(J25="","",K24+1) | L25: =IF(J25="","",L24-M24) | M25: =IF(J25="","",IF(J25=D$21+1,(C$21/D$21)*(I$21/360),C$21/D$21)) | N25: =IF(J25="","",N24+M25) | O25: =IF(J25="","",L25-M25)
J26: =IF(J25="","",IF(J25+1>D$21+1,"",J25+1)) | K26: =IF(J26="","",K25+1) | L26: =IF(J26="","",L25-M25) | M26: =IF(J26="","",IF(J26=D$21+1,(C$21/D$21)*(I$21/360),C$21/D$21)) | N26: =IF(J26="","",N25+M26) | O26: =IF(J26="","",L26-M26)
B28: =B21+1 -> 4 | C28: 3003.26 | D28: 3 | E28: 45401 | F28: 45292 | G28: =YEAR(F28) -> 2024 | H28: =IF(OR(E28="",F28=""),"",(360-(E28-F28))) -> 251 | I28: =IF(OR(E28="",F28=""),"",360-H28) -> 109 | J28: =IF(OR(D28="",C28="",H28=""),"",1) -> 1 | K28: =IF(G28="","",G28) -> 2024 | L28: =IF(C28="","",C28) -> 3003.26 | M28: =IF(OR(J28="",H28=""),"",(C$28/D$28)*H28/360) -> 697.97987 | N28: =M28 -> 697.97987 | O28: =IF(J28="","",L28-M28) -> 2305.2801
J29: =IF(J28="","",IF(J28+1>D$28+1,"",J28+1)) -> 2 | K29: =IF(J29="","",K28+1) -> 2025 | L29: =IF(J29="","",L28-M28) -> 2305.2801 | M29: =IF(J29="","",IF(J29=D$28+1,(C$28/D$28)*(I$28/360),C$28/D$28)) -> 1001.0867 | N29: =IF(J29="","",N28+M29) -> 1699.0665 | O29: =IF(J29="","",L29-M29) -> 1304.1935
J30: =IF(J29="","",IF(J29+1>D$28+1,"",J29+1)) -> 3 | K30: =IF(J30="","",K29+1) -> 2026 | L30: =IF(J30="","",L29-M29) -> 1304.1935 | M30: =IF(J30="","",IF(J30=D$28+1,(C$28/D$28)*(I$28/360),C$28/D$28)) -> 1001.0867 | N30: =IF(J30="","",N29+M30) -> 2700.1532 | O30: =IF(J30="","",L30-M30) -> 303.1068
J31: =IF(J30="","",IF(J30+1>D$28+1,"",J30+1)) -> 4 | K31: =IF(J31="","",K30+1) -> 2027 | L31: =IF(J31="","",L30-M30) -> 303.1068 | M31: =IF(J31="","",IF(J31=D$28+1,(C$28/D$28)*(I$28/360),C$28/D$28)) -> 303.1068 | N31: =IF(J31="","",N30+M31) -> 3003.26 | O31: =IF(J31="","",L31-M31) -> 1.7053026e-13
J32: =IF(J31="","",IF(J31+1>D$28+1,"",J31+1)) | K32: =IF(J32="","",K31+1) | L32: =IF(J32="","",L31-M31) | M32: =IF(J32="","",IF(J32=D$28+1,(C$28/D$28)*(I$28/360),C$28/D$28)) | N32: =IF(J32="","",N31+M32) | O32: =IF(J32="","",L32-M32)
J33: =IF(J32="","",IF(J32+1>D$28+1,"",J32+1)) | K33: =IF(J33="","",K32+1) | L33: =IF(J33="","",L32-M32) | M33: =IF(J33="","",IF(J33=D$28+1,(C$28/D$28)*(I$28/360),C$28/D$28)) | N33: =IF(J33="","",N32+M33) | O33: =IF(J33="","",L33-M33)
B35: =B28+1 -> 5 | G35: =YEAR(F35) -> 1900 | H35: =IF(OR(E35="",F35=""),"",(360-(E35-F35))) | I35: =IF(OR(E35="",F35=""),"",360-H35) | J35: =IF(OR(D35="",C35="",H35=""),"",1) | K35: =IF(G35="","",G35) -> 1900 | L35: =IF(C35="","",C35) | M35: =IF(OR(J35="",H35=""),"",(C$35/D$35)*H35/360) | N35: =M35 | O35: =IF(J35="","",L35-M35)
J36: =IF(J35="","",IF(J35+1>D$35+1,"",J35+1)) | K36: =IF(J36="","",K35+1) | L36: =IF(J36="","",L35-M35) | M36: =IF(J36="","",IF(J36=D$35+1,(C$35/D$35)*(I$35/360),C$35/D$7)) | N36: =IF(J36="","",N35+M36) | O36: =IF(J36="","",L36-M36)
J37: =IF(J36="","",IF(J36+1>D$35+1,"",J36+1)) | K37: =IF(J37="","",K36+1) | L37: =IF(J37="","",L36-M36) | M37: =IF(J37="","",IF(J37=D$35+1,(C$35/D$35)*(I$35/360),C$35/D$7)) | N37: =IF(J37="","",N36+M37) | O37: =IF(J37="","",L37-M37)
J38: =IF(J37="","",IF(J37+1>D$35+1,"",J37+1)) | K38: =IF(J38="","",K37+1) | L38: =IF(J38="","",L37-M37) | M38: =IF(J38="","",IF(J38=D$35+1,(C$35/D$35)*(I$35/360),C$35/D$7)) | N38: =IF(J38="","",N37+M38) | O38: =IF(J38="","",L38-M38)
J39: =IF(J38="","",IF(J38+1>D$35+1,"",J38+1)) | K39: =IF(J39="","",K38+1) | L39: =IF(J39="","",L38-M38) | M39: =IF(J39="","",IF(J39=D$35+1,(C$35/D$35)*(I$35/360),C$35/D$7)) | N39: =IF(J39="","",N38+M39) | O39: =IF(J39="","",L39-M39)
J40: =IF(J39="","",IF(J39+1>D$35+1,"",J39+1)) | K40: =IF(J40="","",K39+1) | L40: =IF(J40="","",L39-M39) | M40: =IF(J40="","",IF(J40=D$35+1,(C$35/D$35)*(I$35/360),C$35/D$7)) | N40: =IF(J40="","",N39+M40) | O40: =IF(J40="","",L40-M40)
B42: =B35+1 -> 6 | G42: =YEAR(F42) -> 1900 | H42: =IF(OR(E42="",F42=""),"",(360-(E42-F42))) | I42: =IF(OR(E42="",F42=""),"",360-H42) | J42: =IF(OR(D42="",C42="",H42=""),"",1) | K42: =IF(G42="","",G42) -> 1900 | L42: =IF(C42="","",C42) | M42: =IF(OR(J42="",H42=""),"",(C$42/D$42)*H42/360) | N42: =M42 | O42: =IF(J42="","",L42-M42)
J43: =IF(J42="","",IF(J42+1>D$42+1,"",J42+1)) | K43: =IF(J43="","",K42+1) | L43: =IF(J43="","",L42-M42) | M43: =IF(J43="","",IF(J43=D$42+1,(C$42/D$42)*(I$42/360),C$42/D$42)) | N43: =IF(J43="","",N42+M43) | O43: =IF(J43="","",L43-M43)
J44: =IF(J43="","",IF(J43+1>D$42+1,"",J43+1)) | K44: =IF(J44="","",K43+1) | L44: =IF(J44="","",L43-M43) | M44: =IF(J44="","",IF(J44=D$42+1,(C$42/D$42)*(I$42/360),C$42/D$42)) | N44: =IF(J44="","",N43+M44) | O44: =IF(J44="","",L44-M44)
J45: =IF(J44="","",IF(J44+1>D$42+1,"",J44+1)) | K45: =IF(J45="","",K44+1) | L45: =IF(J45="","",L44-M44) | M45: =IF(J45="","",IF(J45=D$42+1,(C$42/D$42)*(I$42/360),C$42/D$42)) | N45: =IF(J45="","",N44+M45) | O45: =IF(J45="","",L45-M45)
J46: =IF(J45="","",IF(J45+1>D$42+1,"",J45+1)) | K46: =IF(J46="","",K45+1) | L46: =IF(J46="","",L45-M45) | M46: =IF(J46="","",IF(J46=D$42+1,(C$42/D$42)*(I$42/360),C$42/D$42)) | N46: =IF(J46="","",N45+M46) | O46: =IF(J46="","",L46-M46)
J47: =IF(J46="","",IF(J46+1>D$42+1,"",J46+1)) | K47: =IF(J47="","",K46+1) | L47: =IF(J47="","",L46-M46) | M47: =IF(J47="","",IF(J47=D$42+1,(C$42/D$42)*(I$42/360),C$42/D$42)) | N47: =IF(J47="","",N46+M47) | O47: =IF(J47="","",L47-M47)
B49: =B42+1 -> 7 | G49: =YEAR(F49) -> 1900 | H49: =IF(OR(E49="",F49=""),"",(360-(E49-F49))) | I49: =IF(OR(E49="",F49=""),"",360-H49) | J49: =IF(OR(D49="",C49="",H49=""),"",1) | K49: =IF(G49="","",G49) -> 1900 | L49: =IF(C49="","",C49) | M49: =IF(OR(J49="",H49=""),"",(C$49/D$49)*H49/360) | N49: =M49 | O49: =IF(J49="","",L49-M49)
J50: =IF(J49="","",IF(J49+1>D$49+1,"",J49+1)) | K50: =IF(J50="","",K49+1) | L50: =IF(J50="","",L49-M49) | M50: =IF(J50="","",IF(J50=D$49+1,(C$49/D$49)*(I$49/360),C$49/D$49)) | N50: =IF(J50="","",N49+M50) | O50: =IF(J50="","",L50-M50)
J51: =IF(J50="","",IF(J50+1>D$49+1,"",J50+1)) | K51: =IF(J51="","",K50+1) | L51: =IF(J51="","",L50-M50) | M51: =IF(J51="","",IF(J51=D$49+1,(C$49/D$49)*(I$49/360),C$49/D$49)) | N51: =IF(J51="","",N50+M51) | O51: =IF(J51="","",L51-M51)
J52: =IF(J51="","",IF(J51+1>D$49+1,"",J51+1)) | K52: =IF(J52="","",K51+1) | L52: =IF(J52="","",L51-M51) | M52: =IF(J52="","",IF(J52=D$49+1,(C$49/D$49)*(I$49/360),C$49/D$49)) | N52: =IF(J52="","",N51+M52) | O52: =IF(J52="","",L52-M52)
J53: =IF(J52="","",IF(J52+1>D$49+1,"",J52+1)) | K53: =IF(J53="","",K52+1) | L53: =IF(J53="","",L52-M52) | M53: =IF(J53="","",IF(J53=D$49+1,(C$49/D$49)*(I$49/360),C$49/D$49)) | N53: =IF(J53="","",N52+M53) | O53: =IF(J53="","",L53-M53)
J54: =IF(J53="","",IF(J53+1>D$49+1,"",J53+1)) | K54: =IF(J54="","",K53+1) | L54: =IF(J54="","",L53-M53) | M54: =IF(J54="","",IF(J54=D$49+1,(C$49/D$49)*(I$49/360),C$49/D$49)) | N54: =IF(J54="","",N53+M54) | O54: =IF(J54="","",L54-M54)
B56: =B49+1 -> 8 | G56: =YEAR(F56) -> 1900 | H56: =IF(OR(E56="",F56=""),"",(360-(E56-F56))) | I56: =IF(OR(E56="",F56=""),"",360-H56) | J56: =IF(OR(D56="",C56="",H56=""),"",1) | K56: =IF(G56="","",G56) -> 1900 | L56: =IF(C56="","",C56) | M56: =IF(OR(J56="",H56=""),"",(C$56/D$56)*H56/360) | N56: =M56 | O56: =IF(J56="","",L56-M56)
J57: =IF(J56="","",IF(J56+1>D$56+1,"",J56+1)) | K57: =IF(J57="","",K56+1) | L57: =IF(J57="","",L56-M56) | M57: =IF(J57="","",IF(J57=D$56+1,(C$56/D$56)*(I$56/360),C$56/D$56)) | N57: =IF(J57="","",N56+M57) | O57: =IF(J57="","",L57-M57)
J58: =IF(J57="","",IF(J57+1>D$56+1,"",J57+1)) | K58: =IF(J58="","",K57+1) | L58: =IF(J58="","",L57-M57) | M58: =IF(J58="","",IF(J58=D$56+1,(C$56/D$56)*(I$56/360),C$56/D$56)) | N58: =IF(J58="","",N57+M58) | O58: =IF(J58="","",L58-M58)
J59: =IF(J58="","",IF(J58+1>D$56+1,"",J58+1)) | K59: =IF(J59="","",K58+1) | L59: =IF(J59="","",L58-M58) | M59: =IF(J59="","",IF(J59=D$56+1,(C$56/D$56)*(I$56/360),C$56/D$56)) | N59: =IF(J59="","",N58+M59) | O59: =IF(J59="","",L59-M59)
J60: =IF(J59="","",IF(J59+1>D$56+1,"",J59+1)) | K60: =IF(J60="","",K59+1) | L60: =IF(J60="","",L59-M59) | M60: =IF(J60="","",IF(J60=D$56+1,(C$56/D$56)*(I$56/360),C$56/D$56)) | N60: =IF(J60="","",N59+M60) | O60: =IF(J60="","",L60-M60)
J61: =IF(J60="","",IF(J60+1>D$56+1,"",J60+1)) | K61: =IF(J61="","",K60+1) | L61: =IF(J61="","",L60-M60) | M61: =IF(J61="","",IF(J61=D$56+1,(C$56/D$56)*(I$56/360),C$56/D$56)) | N61: =IF(J61="","",N60+M61) | O61: =IF(J61="","",L61-M61)

Sheet AMM B
C2: NEW LIFE Sàrl - Luxembourg | I2: 2025 | J2: Tableau d'Amortissement Linéaire | Q2: TOTALI
B4: B | C4: VEHICULES MOTEUR
B6: Nr | C6: Valeur du bien | D6: Nombre années amortissement | E6: Date acquisition | F6: Date début exercise | H6: Durée utilisation 1er année | I6: Durée utilisation dernière année | J6: Nr années | K6: Année | L6: Valeur comptable début d'exercise | M6: Annuité d'amortissement | N6: Amortissements cumulés | O6: Valeur nette comptable en fin d'exercice | Q6: Année | R6: Valeur comptable début d'exercise | S6: Annuité d'amortissement | T6: Amortissements cumulés | U6: Valeur nette comptable en fin d'exercice
B7: 1 | C7: =25562.82-8000 -> 17562.82 | D7: 5 | E7: 44742 | F7: 44562 | G7: =YEAR(F7) -> 2022 | H7: =IF(OR(E7="",F7=""),"",(360-(E7-F7))) -> 180 | I7: =IF(OR(E7="",F7=""),"",360-H7) -> 180 | J7: =IF(OR(D7="",C7="",H7=""),"",1) -> 1 | K7: =IF(G7="","",G7) -> 2022 | L7: =IF(C7="","",C7) -> 17562.82 | M7: =IF(OR(J7="",H7=""),"",(C$7/D$7)*H7/360) -> 1756.282 | N7: =M7 -> 1756.282 | O7: =IF(J7="","",L7-M7) -> 15806.538 | Q7: 2022 | R7: =SUMIF($K$7:$K$61,Q7,$L$7:$L$61) -> 17562.82 | S7: =SUMIF($K$7:$K$61,Q7,$M$7:$M$61) -> 1756.282 | T7: =SUMIF($K$7:$K$61,Q7,$N$7:$N$61) -> 1756.282 | U7: =SUMIF($K$7:$K$61,Q7,$O$7:$O$61) -> 15806.538
C8: Car Avenue Peugeot Luxembourg | E8: Vehicule moteur | J8: =IF(J7="","",IF(J7+1>D$7+1,"",J7+1)) -> 2 | K8: =IF(J8="","",K7+1) -> 2023 | L8: =IF(J8="","",L7-M7) -> 15806.538 | M8: =IF(J8="","",IF(J8=D$7+1,(C$7/D$7)*(I$7/360),C$7/D$7)) -> 3512.564 | N8: =IF(J8="","",N7+M8) -> 5268.846 | O8: =IF(J8="","",L8-M8) -> 12293.974 | Q8: =Q7+1 -> 2023 | R8: =SUMIF($K$7:$K$61,Q8,$L$7:$L$61) -> 15806.538 | S8: =SUMIF($K$7:$K$61,Q8,$M$7:$M$61) -> 3512.564 | T8: =SUMIF($K$7:$K$61,Q8,$N$7:$N$61) -> 5268.846 | U8: =SUMIF($K$7:$K$61,Q8,$O$7:$O$61) -> 12293.974
J9: =IF(J8="","",IF(J8+1>D$7+1,"",J8+1)) -> 3 | K9: =IF(J9="","",K8+1) -> 2024 | L9: =IF(J9="","",L8-M8) -> 12293.974 | M9: =IF(J9="","",IF(J9=D$7+1,(C$7/D$7)*(I$7/360),C$7/D$7)) -> 3512.564 | N9: =IF(J9="","",N8+M9) -> 8781.41 | O9: =IF(J9="","",L9-M9) -> 8781.41 | Q9: =Q8+1 -> 2024 | R9: =SUMIF($K$7:$K$61,Q9,$L$7:$L$61) -> 12293.974 | S9: =SUMIF($K$7:$K$61,Q9,$M$7:$M$61) -> 3512.564 | T9: =SUMIF($K$7:$K$61,Q9,$N$7:$N$61) -> 8781.41 | U9: =SUMIF($K$7:$K$61,Q9,$O$7:$O$61) -> 8781.41
J10: =IF(J9="","",IF(J9+1>D$7+1,"",J9+1)) -> 4 | K10: =IF(J10="","",K9+1) -> 2025 | L10: =IF(J10="","",L9-M9) -> 8781.41 | M10: =IF(J10="","",IF(J10=D$7+1,(C$7/D$7)*(I$7/360),C$7/D$7)) -> 3512.564 | N10: =IF(J10="","",N9+M10) -> 12293.974 | O10: =IF(J10="","",L10-M10) -> 5268.846 | Q10: =Q9+1 -> 2025 | R10: =SUMIF($K$7:$K$61,Q10,$L$7:$L$61) -> 8781.41 | S10: =SUMIF($K$7:$K$61,Q10,$M$7:$M$61) -> 3512.564 | T10: =SUMIF($K$7:$K$61,Q10,$N$7:$N$61) -> 12293.974 | U10: =SUMIF($K$7:$K$61,Q10,$O$7:$O$61) -> 5268.846
J11: =IF(J10="","",IF(J10+1>D$7+1,"",J10+1)) -> 5 | K11: =IF(J11="","",K10+1) -> 2026 | L11: =IF(J11="","",L10-M10) -> 5268.846 | M11: =IF(J11="","",IF(J11=D$7+1,(C$7/D$7)*(I$7/360),C$7/D$7)) -> 3512.564 | N11: =IF(J11="","",N10+M11) -> 15806.538 | O11: =IF(J11="","",L11-M11) -> 1756.282 | Q11: =Q10+1 -> 2026 | R11: =SUMIF($K$7:$K$61,Q11,$L$7:$L$61) -> 39196.176 | S11: =SUMIF($K$7:$K$61,Q11,$M$7:$M$61) -> 8601.6635 | T11: =SUMIF($K$7:$K$61,Q11,$N$7:$N$61) -> 20895.638 | U11: =SUMIF($K$7:$K$61,Q11,$O$7:$O$61) -> 30594.513
J12: =IF(J11="","",IF(J11+1>D$7+1,"",J11+1)) -> 6 | K12: =IF(J12="","",K11+1) -> 2027 | L12: =IF(J12="","",L11-M11) -> 1756.282 | M12: =IF(J12="","",IF(J12=D$7+1,(C$7/D$7)*(I$7/360),C$7/D$7)) -> 1756.282 | N12: =IF(J12="","",N11+M12) -> 17562.82 | O12: =IF(J12="","",L12-M12) -> -2.2737368e-13 | Q12: =Q11+1 -> 2027 | R12: =SUMIF($K$7:$K$61,Q12,$L$7:$L$61) -> 30594.513 | S12: =SUMIF($K$7:$K$61,Q12,$M$7:$M$61) -> 8541.748 | T12: =SUMIF($K$7:$K$61,Q12,$N$7:$N$61) -> 29437.386 | U12: =SUMIF($K$7:$K$61,Q12,$O$7:$O$61) -> 22052.765
Q13: =Q12+1 -> 2028 | R13: =SUMIF($K$7:$K$61,Q13,$L$7:$L$61) -> 22052.765 | S13: =SUMIF($K$7:$K$61,Q13,$M$7:$M$61) -> 6785.466 | T13: =SUMIF($K$7:$K$61,Q13,$N$7:$N$61) -> 18660.032 | U13: =SUMIF($K$7:$K$61,Q13,$O$7:$O$61) -> 15267.299
B14: =B7+1 -> 2 | C14: 33927.33 | D14: 5 | E14: 46113 | F14: 46023 | G14: =YEAR(F14) -> 2026 | H14: =IF(OR(E14="",F14=""),"",(360-(E14-F14))) -> 270 | I14: =IF(OR(E14="",F14=""),"",360-H14) -> 90 | J14: =IF(OR(D14="",C14="",H14=""),"",1) -> 1 | K14: =IF(G14="","",G14) -> 2026 | L14: =IF(C14="","",C14) -> 33927.33 | M14: =IF(OR(J14="",H14=""),"",(C$14/D$14)*H14/360) -> 5089.0995 | N14: =M14 -> 5089.0995 | O14: =IF(J14="","",L14-M14) -> 28838.231 | Q14: =Q13+1 -> 2029 | R14: =SUMIF($K$7:$K$61,Q14,$L$7:$L$61) -> 15267.299 | S14: =SUMIF($K$7:$K$61,Q14,$M$7:$M$61) -> 6785.466 | T14: =SUMIF($K$7:$K$61,Q14,$N$7:$N$61) -> 25445.498 | U14: =SUMIF($K$7:$K$61,Q14,$O$7:$O$61) -> 8481.8325
J15: =IF(J14="","",IF(J14+1>D$14+1,"",J14+1)) -> 2 | K15: =IF(J15="","",K14+1) -> 2027 | L15: =IF(J15="","",L14-M14) -> 28838.231 | M15: =IF(J15="","",IF(J15=D$14+1,(C$14/D$14)*(I$14/360),C$14/D$14)) -> 6785.466 | N15: =IF(J15="","",N14+M15) -> 11874.566 | O15: =IF(J15="","",L15-M15) -> 22052.765 | Q15: =Q14+1 -> 2030 | R15: =SUMIF($K$7:$K$61,Q15,$L$7:$L$61) -> 8481.8325 | S15: =SUMIF($K$7:$K$61,Q15,$M$7:$M$61) -> 6785.466 | T15: =SUMIF($K$7:$K$61,Q15,$N$7:$N$61) -> 32230.964 | U15: =SUMIF($K$7:$K$61,Q15,$O$7:$O$61) -> 1696.3665
J16: =IF(J15="","",IF(J15+1>D$14+1,"",J15+1)) -> 3 | K16: =IF(J16="","",K15+1) -> 2028 | L16: =IF(J16="","",L15-M15) -> 22052.765 | M16: =IF(J16="","",IF(J16=D$14+1,(C$14/D$14)*(I$14/360),C$14/D$14)) -> 6785.466 | N16: =IF(J16="","",N15+M16) -> 18660.032 | O16: =IF(J16="","",L16-M16) -> 15267.299
J17: =IF(J16="","",IF(J16+1>D$14+1,"",J16+1)) -> 4 | K17: =IF(J17="","",K16+1) -> 2029 | L17: =IF(J17="","",L16-M16) -> 15267.299 | M17: =IF(J17="","",IF(J17=D$14+1,(C$14/D$14)*(I$14/360),C$14/D$14)) -> 6785.466 | N17: =IF(J17="","",N16+M17) -> 25445.498 | O17: =IF(J17="","",L17-M17) -> 8481.8325
J18: =IF(J17="","",IF(J17+1>D$14+1,"",J17+1)) -> 5 | K18: =IF(J18="","",K17+1) -> 2030 | L18: =IF(J18="","",L17-M17) -> 8481.8325 | M18: =IF(J18="","",IF(J18=D$14+1,(C$14/D$14)*(I$14/360),C$14/D$14)) -> 6785.466 | N18: =IF(J18="","",N17+M18) -> 32230.964 | O18: =IF(J18="","",L18-M18) -> 1696.3665
J19: =IF(J18="","",IF(J18+1>D$14+1,"",J18+1)) -> 6 | K19: =IF(J19="","",K18+1) -> 2031 | L19: =IF(J19="","",L18-M18) -> 1696.3665 | M19: =IF(J19="","",IF(J19=D$14+1,(C$14/D$14)*(I$14/360),C$14/D$14)) -> 1696.3665 | N19: =IF(J19="","",N18+M19) -> 33927.33 | O19: =IF(J19="","",L19-M19) -> 0
B21: =B14+1 -> 3 | G21: =YEAR(F21) -> 1900 | H21: =IF(OR(E21="",F21=""),"",(360-(E21-F21))) | I21: =IF(OR(E21="",F21=""),"",360-H21) | J21: =IF(OR(D21="",C21="",H21=""),"",1) | K21: =IF(G21="","",G21) -> 1900 | L21: =IF(C21="","",C21) | M21: =IF(OR(J21="",H21=""),"",(C$21/D$21)*H21/360) | N21: =M21 | O21: =IF(J21="","",L21-M21)
J22: =IF(J21="","",IF(J21+1>D$21+1,"",J21+1)) | K22: =IF(J22="","",K21+1) | L22: =IF(J22="","",L21-M21) | M22: =IF(J22="","",IF(J22=D$21+1,(C$21/D$21)*(I$21/360),C$21/D$21)) | N22: =IF(J22="","",N21+M22) | O22: =IF(J22="","",L22-M22)
J23: =IF(J22="","",IF(J22+1>D$21+1,"",J22+1)) | K23: =IF(J23="","",K22+1) | L23: =IF(J23="","",L22-M22) | M23: =IF(J23="","",IF(J23=D$21+1,(C$21/D$21)*(I$21/360),C$21/D$21)) | N23: =IF(J23="","",N22+M23) | O23: =IF(J23="","",L23-M23)
J24: =IF(J23="","",IF(J23+1>D$21+1,"",J23+1)) | K24: =IF(J24="","",K23+1) | L24: =IF(J24="","",L23-M23) | M24: =IF(J24="","",IF(J24=D$21+1,(C$21/D$21)*(I$21/360),C$21/D$21)) | N24: =IF(J24="","",N23+M24) | O24: =IF(J24="","",L24-M24)
J25: =IF(J24="","",IF(J24+1>D$21+1,"",J24+1)) | K25: =IF(J25="","",K24+1) | L25: =IF(J25="","",L24-M24) | M25: =IF(J25="","",IF(J25=D$21+1,(C$21/D$21)*(I$21/360),C$21/D$21)) | N25: =IF(J25="","",N24+M25) | O25: =IF(J25="","",L25-M25)
J26: =IF(J25="","",IF(J25+1>D$21+1,"",J25+1)) | K26: =IF(J26="","",K25+1) | L26: =IF(J26="","",L25-M25) | M26: =IF(J26="","",IF(J26=D$21+1,(C$21/D$21)*(I$21/360),C$21/D$21)) | N26: =IF(J26="","",N25+M26) | O26: =IF(J26="","",L26-M26)
B28: =B21+1 -> 4 | G28: =YEAR(F28) -> 1900 | H28: =IF(OR(E28="",F28=""),"",(360-(E28-F28))) | I28: =IF(OR(E28="",F28=""),"",360-H28) | J28: =IF(OR(D28="",C28="",H28=""),"",1) | K28: =IF(G28="","",G28) -> 1900 | L28: =IF(C28="","",C28) | M28: =IF(OR(J28="",H28=""),"",(C$28/D$28)*H28/360) | N28: =M28 | O28: =IF(J28="","",L28-M28)
J29: =IF(J28="","",IF(J28+1>D$28+1,"",J28+1)) | K29: =IF(J29="","",K28+1) | L29: =IF(J29="","",L28-M28) | M29: =IF(J29="","",IF(J29=D$28+1,(C$28/D$28)*(I$28/360),C$28/D$28)) | N29: =IF(J29="","",N28+M29) | O29: =IF(J29="","",L29-M29)
J30: =IF(J29="","",IF(J29+1>D$28+1,"",J29+1)) | K30: =IF(J30="","",K29+1) | L30: =IF(J30="","",L29-M29) | M30: =IF(J30="","",IF(J30=D$28+1,(C$28/D$28)*(I$28/360),C$28/D$28)) | N30: =IF(J30="","",N29+M30) | O30: =IF(J30="","",L30-M30)
J31: =IF(J30="","",IF(J30+1>D$28+1,"",J30+1)) | K31: =IF(J31="","",K30+1) | L31: =IF(J31="","",L30-M30) | M31: =IF(J31="","",IF(J31=D$28+1,(C$28/D$28)*(I$28/360),C$28/D$28)) | N31: =IF(J31="","",N30+M31) | O31: =IF(J31="","",L31-M31)
J32: =IF(J31="","",IF(J31+1>D$28+1,"",J31+1)) | K32: =IF(J32="","",K31+1) | L32: =IF(J32="","",L31-M31) | M32: =IF(J32="","",IF(J32=D$28+1,(C$28/D$28)*(I$28/360),C$28/D$28)) | N32: =IF(J32="","",N31+M32) | O32: =IF(J32="","",L32-M32)
J33: =IF(J32="","",IF(J32+1>D$28+1,"",J32+1)) | K33: =IF(J33="","",K32+1) | L33: =IF(J33="","",L32-M32) | M33: =IF(J33="","",IF(J33=D$28+1,(C$28/D$28)*(I$28/360),C$28/D$28)) | N33: =IF(J33="","",N32+M33) | O33: =IF(J33="","",L33-M33)
B35: =B28+1 -> 5 | G35: =YEAR(F35) -> 1900 | H35: =IF(OR(E35="",F35=""),"",(360-(E35-F35))) | I35: =IF(OR(E35="",F35=""),"",360-H35) | J35: =IF(OR(D35="",C35="",H35=""),"",1) | K35: =IF(G35="","",G35) -> 1900 | L35: =IF(C35="","",C35) | M35: =IF(OR(J35="",H35=""),"",(C$35/D$35)*H35/360) | N35: =M35 | O35: =IF(J35="","",L35-M35)
J36: =IF(J35="","",IF(J35+1>D$35+1,"",J35+1)) | K36: =IF(J36="","",K35+1) | L36: =IF(J36="","",L35-M35) | M36: =IF(J36="","",IF(J36=D$35+1,(C$35/D$35)*(I$35/360),C$35/D$7)) | N36: =IF(J36="","",N35+M36) | O36: =IF(J36="","",L36-M36)
J37: =IF(J36="","",IF(J36+1>D$35+1,"",J36+1)) | K37: =IF(J37="","",K36+1) | L37: =IF(J37="","",L36-M36) | M37: =IF(J37="","",IF(J37=D$35+1,(C$35/D$35)*(I$35/360),C$35/D$7)) | N37: =IF(J37="","",N36+M37) | O37: =IF(J37="","",L37-M37)
J38: =IF(J37="","",IF(J37+1>D$35+1,"",J37+1)) | K38: =IF(J38="","",K37+1) | L38: =IF(J38="","",L37-M37) | M38: =IF(J38="","",IF(J38=D$35+1,(C$35/D$35)*(I$35/360),C$35/D$7)) | N38: =IF(J38="","",N37+M38) | O38: =IF(J38="","",L38-M38)
J39: =IF(J38="","",IF(J38+1>D$35+1,"",J38+1)) | K39: =IF(J39="","",K38+1) | L39: =IF(J39="","",L38-M38) | M39: =IF(J39="","",IF(J39=D$35+1,(C$35/D$35)*(I$35/360),C$35/D$7)) | N39: =IF(J39="","",N38+M39) | O39: =IF(J39="","",L39-M39)
J40: =IF(J39="","",IF(J39+1>D$35+1,"",J39+1)) | K40: =IF(J40="","",K39+1) | L40: =IF(J40="","",L39-M39) | M40: =IF(J40="","",IF(J40=D$35+1,(C$35/D$35)*(I$35/360),C$35/D$7)) | N40: =IF(J40="","",N39+M40) | O40: =IF(J40="","",L40-M40)
B42: =B35+1 -> 6 | G42: =YEAR(F42) -> 1900 | H42: =IF(OR(E42="",F42=""),"",(360-(E42-F42))) | I42: =IF(OR(E42="",F42=""),"",360-H42) | J42: =IF(OR(D42="",C42="",H42=""),"",1) | K42: =IF(G42="","",G42) -> 1900 | L42: =IF(C42="","",C42) | M42: =IF(OR(J42="",H42=""),"",(C$42/D$42)*H42/360) | N42: =M42 | O42: =IF(J42="","",L42-M42)
J43: =IF(J42="","",IF(J42+1>D$42+1,"",J42+1)) | K43: =IF(J43="","",K42+1) | L43: =IF(J43="","",L42-M42) | M43: =IF(J43="","",IF(J43=D$42+1,(C$42/D$42)*(I$42/360),C$42/D$42)) | N43: =IF(J43="","",N42+M43) | O43: =IF(J43="","",L43-M43)
J44: =IF(J43="","",IF(J43+1>D$42+1,"",J43+1)) | K44: =IF(J44="","",K43+1) | L44: =IF(J44="","",L43-M43) | M44: =IF(J44="","",IF(J44=D$42+1,(C$42/D$42)*(I$42/360),C$42/D$42)) | N44: =IF(J44="","",N43+M44) | O44: =IF(J44="","",L44-M44)
J45: =IF(J44="","",IF(J44+1>D$42+1,"",J44+1)) | K45: =IF(J45="","",K44+1) | L45: =IF(J45="","",L44-M44) | M45: =IF(J45="","",IF(J45=D$42+1,(C$42/D$42)*(I$42/360),C$42/D$42)) | N45: =IF(J45="","",N44+M45) | O45: =IF(J45="","",L45-M45)
J46: =IF(J45="","",IF(J45+1>D$42+1,"",J45+1)) | K46: =IF(J46="","",K45+1) | L46: =IF(J46="","",L45-M45) | M46: =IF(J46="","",IF(J46=D$42+1,(C$42/D$42)*(I$42/360),C$42/D$42)) | N46: =IF(J46="","",N45+M46) | O46: =IF(J46="","",L46-M46)
J47: =IF(J46="","",IF(J46+1>D$42+1,"",J46+1)) | K47: =IF(J47="","",K46+1) | L47: =IF(J47="","",L46-M46) | M47: =IF(J47="","",IF(J47=D$42+1,(C$42/D$42)*(I$42/360),C$42/D$42)) | N47: =IF(J47="","",N46+M47) | O47: =IF(J47="","",L47-M47)
B49: =B42+1 -> 7 | G49: =YEAR(F49) -> 1900 | H49: =IF(OR(E49="",F49=""),"",(360-(E49-F49))) | I49: =IF(OR(E49="",F49=""),"",360-H49) | J49: =IF(OR(D49="",C49="",H49=""),"",1) | K49: =IF(G49="","",G49) -> 1900 | L49: =IF(C49="","",C49) | M49: =IF(OR(J49="",H49=""),"",(C$49/D$49)*H49/360) | N49: =M49 | O49: =IF(J49="","",L49-M49)
J50: =IF(J49="","",IF(J49+1>D$49+1,"",J49+1)) | K50: =IF(J50="","",K49+1) | L50: =IF(J50="","",L49-M49) | M50: =IF(J50="","",IF(J50=D$49+1,(C$49/D$49)*(I$49/360),C$49/D$49)) | N50: =IF(J50="","",N49+M50) | O50: =IF(J50="","",L50-M50)
J51: =IF(J50="","",IF(J50+1>D$49+1,"",J50+1)) | K51: =IF(J51="","",K50+1) | L51: =IF(J51="","",L50-M50) | M51: =IF(J51="","",IF(J51=D$49+1,(C$49/D$49)*(I$49/360),C$49/D$49)) | N51: =IF(J51="","",N50+M51) | O51: =IF(J51="","",L51-M51)
J52: =IF(J51="","",IF(J51+1>D$49+1,"",J51+1)) | K52: =IF(J52="","",K51+1) | L52: =IF(J52="","",L51-M51) | M52: =IF(J52="","",IF(J52=D$49+1,(C$49/D$49)*(I$49/360),C$49/D$49)) | N52: =IF(J52="","",N51+M52) | O52: =IF(J52="","",L52-M52)
J53: =IF(J52="","",IF(J52+1>D$49+1,"",J52+1)) | K53: =IF(J53="","",K52+1) | L53: =IF(J53="","",L52-M52) | M53: =IF(J53="","",IF(J53=D$49+1,(C$49/D$49)*(I$49/360),C$49/D$49)) | N53: =IF(J53="","",N52+M53) | O53: =IF(J53="","",L53-M53)
J54: =IF(J53="","",IF(J53+1>D$49+1,"",J53+1)) | K54: =IF(J54="","",K53+1) | L54: =IF(J54="","",L53-M53) | M54: =IF(J54="","",IF(J54=D$49+1,(C$49/D$49)*(I$49/360),C$49/D$49)) | N54: =IF(J54="","",N53+M54) | O54: =IF(J54="","",L54-M54)
B56: =B49+1 -> 8 | G56: =YEAR(F56) -> 1900 | H56: =IF(OR(E56="",F56=""),"",(360-(E56-F56))) | I56: =IF(OR(E56="",F56=""),"",360-H56) | J56: =IF(OR(D56="",C56="",H56=""),"",1) | K56: =IF(G56="","",G56) -> 1900 | L56: =IF(C56="","",C56) | M56: =IF(OR(J56="",H56=""),"",(C$56/D$56)*H56/360) | N56: =M56 | O56: =IF(J56="","",L56-M56)
J57: =IF(J56="","",IF(J56+1>D$56+1,"",J56+1)) | K57: =IF(J57="","",K56+1) | L57: =IF(J57="","",L56-M56) | M57: =IF(J57="","",IF(J57=D$56+1,(C$56/D$56)*(I$56/360),C$56/D$56)) | N57: =IF(J57="","",N56+M57) | O57: =IF(J57="","",L57-M57)
J58: =IF(J57="","",IF(J57+1>D$56+1,"",J57+1)) | K58: =IF(J58="","",K57+1) | L58: =IF(J58="","",L57-M57) | M58: =IF(J58="","",IF(J58=D$56+1,(C$56/D$56)*(I$56/360),C$56/D$56)) | N58: =IF(J58="","",N57+M58) | O58: =IF(J58="","",L58-M58)
J59: =IF(J58="","",IF(J58+1>D$56+1,"",J58+1)) | K59: =IF(J59="","",K58+1) | L59: =IF(J59="","",L58-M58) | M59: =IF(J59="","",IF(J59=D$56+1,(C$56/D$56)*(I$56/360),C$56/D$56)) | N59: =IF(J59="","",N58+M59) | O59: =IF(J59="","",L59-M59)
J60: =IF(J59="","",IF(J59+1>D$56+1,"",J59+1)) | K60: =IF(J60="","",K59+1) | L60: =IF(J60="","",L59-M59) | M60: =IF(J60="","",IF(J60=D$56+1,(C$56/D$56)*(I$56/360),C$56/D$56)) | N60: =IF(J60="","",N59+M60) | O60: =IF(J60="","",L60-M60)
J61: =IF(J60="","",IF(J60+1>D$56+1,"",J60+1)) | K61: =IF(J61="","",K60+1) | L61: =IF(J61="","",L60-M60) | M61: =IF(J61="","",IF(J61=D$56+1,(C$56/D$56)*(I$56/360),C$56/D$56)) | N61: =IF(J61="","",N60+M61) | O61: =IF(J61="","",L61-M61)

Sheet AMM C
C2: NEW LIFE Sàrl - Luxembourg | I2: 2025 | J2: Tableau d'Amortissement Linéaire | Q2: TOTALI
C4: MOBILIER
B6: Nr | C6: Valeur du bien | D6: Nombre années amortissement | E6: Date acquisition | F6: Date début exercise | H6: Durée utilisation 1er année | I6: Durée utilisation dernière année | J6: Nr années | K6: Année | L6: Valeur comptable début d'exercise | M6: Annuité d'amortissement | N6: Amortissements cumulés | O6: Valeur nette comptable en fin d'exercice | Q6: Année | R6: Valeur comptable début d'exercise | S6: Annuité d'amortissement | T6: Amortissements cumulés | U6: Valeur nette comptable en fin d'exercice
B7: 1 | C7: 1520 | D7: 5 | E7: 44606 | F7: 44562 | G7: =YEAR(F7) -> 2022 | H7: =IF(OR(E7="",F7=""),"",(360-(E7-F7))) -> 316 | I7: =IF(OR(E7="",F7=""),"",360-H7) -> 44 | J7: =IF(OR(D7="",C7="",H7=""),"",1) -> 1 | K7: =IF(G7="","",G7) -> 2022 | L7: =IF(C7="","",C7) -> 1520 | M7: =IF(OR(J7="",H7=""),"",(C$7/D$7)*H7/360) -> 266.84444 | N7: =M7 -> 266.84444 | O7: =IF(J7="","",L7-M7) -> 1253.1556 | Q7: 2022 | R7: =SUMIF($K$7:$K$61,Q7,$L$7:$L$61) -> 8559.04 | S7: =SUMIF($K$7:$K$61,Q7,$M$7:$M$61) -> 1174.1355 | T7: =SUMIF($K$7:$K$61,Q7,$N$7:$N$61) -> 1174.1355 | U7: =SUMIF($K$7:$K$61,Q7,$O$7:$O$61) -> 7384.9045
C8: Idrosanitaria Piave - Italie | E8: Bureautique | J8: =IF(J7="","",IF(J7+1>D$7+1,"",J7+1)) -> 2 | K8: =IF(J8="","",K7+1) -> 2023 | L8: =IF(J8="","",L7-M7) -> 1253.1556 | M8: =IF(J8="","",IF(J8=D$7+1,(C$7/D$7)*(I$7/360),C$7/D$7)) -> 304 | N8: =IF(J8="","",N7+M8) -> 570.84444 | O8: =IF(J8="","",L8-M8) -> 949.15556 | Q8: =Q7+1 -> 2023 | R8: =SUMIF($K$7:$K$61,Q8,$L$7:$L$61) -> 7384.9045 | S8: =SUMIF($K$7:$K$61,Q8,$M$7:$M$61) -> 1711.808 | T8: =SUMIF($K$7:$K$61,Q8,$N$7:$N$61) -> 2885.9435 | U8: =SUMIF($K$7:$K$61,Q8,$O$7:$O$61) -> 5673.0965
J9: =IF(J8="","",IF(J8+1>D$7+1,"",J8+1)) -> 3 | K9: =IF(J9="","",K8+1) -> 2024 | L9: =IF(J9="","",L8-M8) -> 949.15556 | M9: =IF(J9="","",IF(J9=D$7+1,(C$7/D$7)*(I$7/360),C$7/D$7)) -> 304 | N9: =IF(J9="","",N8+M9) -> 874.84444 | O9: =IF(J9="","",L9-M9) -> 645.15556 | Q9: =Q8+1 -> 2024 | R9: =SUMIF($K$7:$K$61,Q9,$L$7:$L$61) -> 5673.0965 | S9: =SUMIF($K$7:$K$61,Q9,$M$7:$M$61) -> 1711.808 | T9: =SUMIF($K$7:$K$61,Q9,$N$7:$N$61) -> 4597.7515 | U9: =SUMIF($K$7:$K$61,Q9,$O$7:$O$61) -> 3961.2885
J10: =IF(J9="","",IF(J9+1>D$7+1,"",J9+1)) -> 4 | K10: =IF(J10="","",K9+1) -> 2025 | L10: =IF(J10="","",L9-M9) -> 645.15556 | M10: =IF(J10="","",IF(J10=D$7+1,(C$7/D$7)*(I$7/360),C$7/D$7)) -> 304 | N10: =IF(J10="","",N9+M10) -> 1178.8444 | O10: =IF(J10="","",L10-M10) -> 341.15556 | Q10: =Q9+1 -> 2025 | R10: =SUMIF($K$7:$K$61,Q10,$L$7:$L$61) -> 7766.4185 | S10: =SUMIF($K$7:$K$61,Q10,$M$7:$M$61) -> 2092.321 | T10: =SUMIF($K$7:$K$61,Q10,$N$7:$N$61) -> 6690.0725 | U10: =SUMIF($K$7:$K$61,Q10,$O$7:$O$61) -> 5674.0975
J11: =IF(J10="","",IF(J10+1>D$7+1,"",J10+1)) -> 5 | K11: =IF(J11="","",K10+1) -> 2026 | L11: =IF(J11="","",L10-M10) -> 341.15556 | M11: =IF(J11="","",IF(J11=D$7+1,(C$7/D$7)*(I$7/360),C$7/D$7)) -> 304 | N11: =IF(J11="","",N10+M11) -> 1482.8444 | O11: =IF(J11="","",L11-M11) -> 37.155556 | Q11: =Q10+1 -> 2026 | R11: =SUMIF($K$7:$K$61,Q11,$L$7:$L$61) -> 5674.0975 | S11: =SUMIF($K$7:$K$61,Q11,$M$7:$M$61) -> 2472.834 | T11: =SUMIF($K$7:$K$61,Q11,$N$7:$N$61) -> 9162.9065 | U11: =SUMIF($K$7:$K$61,Q11,$O$7:$O$61) -> 3201.2635
J12: =IF(J11="","",IF(J11+1>D$7+1,"",J11+1)) -> 6 | K12: =IF(J12="","",K11+1) -> 2027 | L12: =IF(J12="","",L11-M11) -> 37.155556 | M12: =IF(J12="","",IF(J12=D$7+1,(C$7/D$7)*(I$7/360),C$7/D$7)) -> 37.155556 | N12: =IF(J12="","",N11+M12) -> 1520 | O12: =IF(J12="","",L12-M12) -> 1.4210855e-14 | Q12: =Q11+1 -> 2027 | R12: =SUMIF($K$7:$K$61,Q12,$L$7:$L$61) -> 3201.2635 | S12: =SUMIF($K$7:$K$61,Q12,$M$7:$M$61) -> 1298.6985 | T12: =SUMIF($K$7:$K$61,Q12,$N$7:$N$61) -> 10461.605 | U12: =SUMIF($K$7:$K$61,Q12,$O$7:$O$61) -> 1902.565
Q13: =Q12+1 -> 2028 | R13: =SUMIF($K$7:$K$61,Q13,$L$7:$L$61) -> 1902.565 | S13: =SUMIF($K$7:$K$61,Q13,$M$7:$M$61) -> 761.026 | T13: =SUMIF($K$7:$K$61,Q13,$N$7:$N$61) -> 2663.591 | U13: =SUMIF($K$7:$K$61,Q13,$O$7:$O$61) -> 1141.539
B14: =B7+1 -> 2 | C14: 1020 | D14: 5 | E14: 44664 | F14: 44562 | G14: =YEAR(F14) -> 2022 | H14: =IF(OR(E14="",F14=""),"",(360-(E14-F14))) -> 258 | I14: =IF(OR(E14="",F14=""),"",360-H14) -> 102 | J14: =IF(OR(D14="",C14="",H14=""),"",1) -> 1 | K14: =IF(G14="","",G14) -> 2022 | L14: =IF(C14="","",C14) -> 1020 | M14: =IF(OR(J14="",H14=""),"",(C$14/D$14)*H14/360) -> 146.2 | N14: =M14 -> 146.2 | O14: =IF(J14="","",L14-M14) -> 873.8 | Q14: =Q13+1 -> 2029 | R14: =SUMIF($K$7:$K$61,Q14,$L$7:$L$61) -> 1141.539 | S14: =SUMIF($K$7:$K$61,Q14,$M$7:$M$61) -> 761.026 | T14: =SUMIF($K$7:$K$61,Q14,$N$7:$N$61) -> 3424.617 | U14: =SUMIF($K$7:$K$61,Q14,$O$7:$O$61) -> 380.513
C15: SME S.p.A. - Italie | E15: Bureautique | J15: =IF(J14="","",IF(J14+1>D$14+1,"",J14+1)) -> 2 | K15: =IF(J15="","",K14+1) -> 2023 | L15: =IF(J15="","",L14-M14) -> 873.8 | M15: =IF(J15="","",IF(J15=D$14+1,(C$14/D$14)*(I$14/360),C$14/D$14)) -> 204 | N15: =IF(J15="","",N14+M15) -> 350.2 | O15: =IF(J15="","",L15-M15) -> 669.8 | Q15: =Q14+1 -> 2030 | R15: =SUMIF($K$7:$K$61,Q15,$L$7:$L$61) -> 380.513 | S15: =SUMIF($K$7:$K$61,Q15,$M$7:$M$61) -> 380.513 | T15: =SUMIF($K$7:$K$61,Q15,$N$7:$N$61) -> 3805.13 | U15: =SUMIF($K$7:$K$61,Q15,$O$7:$O$61) -> 1.1368684e-13
J16: =IF(J15="","",IF(J15+1>D$14+1,"",J15+1)) -> 3 | K16: =IF(J16="","",K15+1) -> 2024 | L16: =IF(J16="","",L15-M15) -> 669.8 | M16: =IF(J16="","",IF(J16=D$14+1,(C$14/D$14)*(I$14/360),C$14/D$14)) -> 204 | N16: =IF(J16="","",N15+M16) -> 554.2 | O16: =IF(J16="","",L16-M16) -> 465.8
J17: =IF(J16="","",IF(J16+1>D$14+1,"",J16+1)) -> 4 | K17: =IF(J17="","",K16+1) -> 2025 | L17: =IF(J17="","",L16-M16) -> 465.8 | M17: =IF(J17="","",IF(J17=D$14+1,(C$14/D$14)*(I$14/360),C$14/D$14)) -> 204 | N17: =IF(J17="","",N16+M17) -> 758.2 | O17: =IF(J17="","",L17-M17) -> 261.8
J18: =IF(J17="","",IF(J17+1>D$14+1,"",J17+1)) -> 5 | K18: =IF(J18="","",K17+1) -> 2026 | L18: =IF(J18="","",L17-M17) -> 261.8 | M18: =IF(J18="","",IF(J18=D$14+1,(C$14/D$14)*(I$14/360),C$14/D$14)) -> 204 | N18: =IF(J18="","",N17+M18) -> 962.2 | O18: =IF(J18="","",L18-M18) -> 57.8
J19: =IF(J18="","",IF(J18+1>D$14+1,"",J18+1)) -> 6 | K19: =IF(J19="","",K18+1) -> 2027 | L19: =IF(J19="","",L18-M18) -> 57.8 | M19: =IF(J19="","",IF(J19=D$14+1,(C$14/D$14)*(I$14/360),C$14/D$14)) -> 57.8 | N19: =IF(J19="","",N18+M19) -> 1020 | O19: =IF(J19="","",L19-M19) -> -4.2632564e-14
B21: =B14+1 -> 3 | C21: 3541.67 | D21: 5 | E21: 44681 | F21: 44562 | G21: =YEAR(F21) -> 2022 | H21: =IF(OR(E21="",F21=""),"",(360-(E21-F21))) -> 241 | I21: =IF(OR(E21="",F21=""),"",360-H21) -> 119 | J21: =IF(OR(D21="",C21="",H21=""),"",1) -> 1 | K21: =IF(G21="","",G21) -> 2022 | L21: =IF(C21="","",C21) -> 3541.67 | M21: =IF(OR(J21="",H21=""),"",(C$21/D$21)*H21/360) -> 474.19026 | N21: =M21 -> 474.19026 | O21: =IF(J21="","",L21-M21) -> 3067.4797
C22: Idrosanitaria Piave - Italie | E22: Bureautique | J22: =IF(J21="","",IF(J21+1>D$21+1,"",J21+1)) -> 2 | K22: =IF(J22="","",K21+1) -> 2023 | L22: =IF(J22="","",L21-M21) -> 3067.4797 | M22: =IF(J22="","",IF(J22=D$21+1,(C$21/D$21)*(I$21/360),C$21/D$21)) -> 708.334 | N22: =IF(J22="","",N21+M22) -> 1182.5243 | O22: =IF(J22="","",L22-M22) -> 2359.1457
J23: =IF(J22="","",IF(J22+1>D$21+1,"",J22+1)) -> 3 | K23: =IF(J23="","",K22+1) -> 2024 | L23: =IF(J23="","",L22-M22) -> 2359.1457 | M23: =IF(J23="","",IF(J23=D$21+1,(C$21/D$21)*(I$21/360),C$21/D$21)) -> 708.334 | N23: =IF(J23="","",N22+M23) -> 1890.8583 | O23: =IF(J23="","",L23-M23) -> 1650.8117
J24: =IF(J23="","",IF(J23+1>D$21+1,"",J23+1)) -> 4 | K24: =IF(J24="","",K23+1) -> 2025 | L24: =IF(J24="","",L23-M23) -> 1650.8117 | M24: =IF(J24="","",IF(J24=D$21+1,(C$21/D$21)*(I$21/360),C$21/D$21)) -> 708.334 | N24: =IF(J24="","",N23+M24) -> 2599.1923 | O24: =IF(J24="","",L24-M24) -> 942.47774
J25: =IF(J24="","",IF(J24+1>D$21+1,"",J24+1)) -> 5 | K25: =IF(J25="","",K24+1) -> 2026 | L25: =IF(J25="","",L24-M24) -> 942.47774 | M25: =IF(J25="","",IF(J25=D$21+1,(C$21/D$21)*(I$21/360),C$21/D$21)) -> 708.334 | N25: =IF(J25="","",N24+M25) -> 3307.5263 | O25: =IF(J25="","",L25-M25) -> 234.14374
J26: =IF(J25="","",IF(J25+1>D$21+1,"",J25+1)) -> 6 | K26: =IF(J26="","",K25+1) -> 2027 | L26: =IF(J26="","",L25-M25) -> 234.14374 | M26: =IF(J26="","",IF(J26=D$21+1,(C$21/D$21)*(I$21/360),C$21/D$21)) -> 234.14374 | N26: =IF(J26="","",N25+M26) -> 3541.67 | O26: =IF(J26="","",L26-M26) -> 2.8421709e-13
B28: =B21+1 -> 4 | C28: 1403.31 | D28: 5 | E28: 44691 | F28: 44562 | G28: =YEAR(F28) -> 2022 | H28: =IF(OR(E28="",F28=""),"",(360-(E28-F28))) -> 231 | I28: =IF(OR(E28="",F28=""),"",360-H28) -> 129 | J28: =IF(OR(D28="",C28="",H28=""),"",1) -> 1 | K28: =IF(G28="","",G28) -> 2022 | L28: =IF(C28="","",C28) -> 1403.31 | M28: =IF(OR(J28="",H28=""),"",(C$28/D$28)*H28/360) -> 180.09145 | N28: =M28 -> 180.09145 | O28: =IF(J28="","",L28-M28) -> 1223.2186
C29: IKEA Arlon - Belgique | E29: Bureautique | J29: =IF(J28="","",IF(J28+1>D$28+1,"",J28+1)) -> 2 | K29: =IF(J29="","",K28+1) -> 2023 | L29: =IF(J29="","",L28-M28) -> 1223.2186 | M29: =IF(J29="","",IF(J29=D$28+1,(C$28/D$28)*(I$28/360),C$28/D$28)) -> 280.662 | N29: =IF(J29="","",N28+M29) -> 460.75345 | O29: =IF(J29="","",L29-M29) -> 942.55655
J30: =IF(J29="","",IF(J29+1>D$28+1,"",J29+1)) -> 3 | K30: =IF(J30="","",K29+1) -> 2024 | L30: =IF(J30="","",L29-M29) -> 942.55655 | M30: =IF(J30="","",IF(J30=D$28+1,(C$28/D$28)*(I$28/360),C$28/D$28)) -> 280.662 | N30: =IF(J30="","",N29+M30) -> 741.41545 | O30: =IF(J30="","",L30-M30) -> 661.89455
J31: =IF(J30="","",IF(J30+1>D$28+1,"",J30+1)) -> 4 | K31: =IF(J31="","",K30+1) -> 2025 | L31: =IF(J31="","",L30-M30) -> 661.89455 | M31: =IF(J31="","",IF(J31=D$28+1,(C$28/D$28)*(I$28/360),C$28/D$28)) -> 280.662 | N31: =IF(J31="","",N30+M31) -> 1022.0774 | O31: =IF(J31="","",L31-M31) -> 381.23255
J32: =IF(J31="","",IF(J31+1>D$28+1,"",J31+1)) -> 5 | K32: =IF(J32="","",K31+1) -> 2026 | L32: =IF(J32="","",L31-M31) -> 381.23255 | M32: =IF(J32="","",IF(J32=D$28+1,(C$28/D$28)*(I$28/360),C$28/D$28)) -> 280.662 | N32: =IF(J32="","",N31+M32) -> 1302.7395 | O32: =IF(J32="","",L32-M32) -> 100.57055
J33: =IF(J32="","",IF(J32+1>D$28+1,"",J32+1)) -> 6 | K33: =IF(J33="","",K32+1) -> 2027 | L33: =IF(J33="","",L32-M32) -> 100.57055 | M33: =IF(J33="","",IF(J33=D$28+1,(C$28/D$28)*(I$28/360),C$28/D$28)) -> 100.57055 | N33: =IF(J33="","",N32+M33) -> 1403.31 | O33: =IF(J33="","",L33-M33) -> 2.8421709e-14
B35: =B28+1 -> 5 | C35: 1074.06 | D35: 5 | E35: 44743 | F35: 44562 | G35: =YEAR(F35) -> 2022 | H35: =IF(OR(E35="",F35=""),"",(360-(E35-F35))) -> 179 | I35: =IF(OR(E35="",F35=""),"",360-H35) -> 181 | J35: =IF(OR(D35="",C35="",H35=""),"",1) -> 1 | K35: =IF(G35="","",G35) -> 2022 | L35: =IF(C35="","",C35) -> 1074.06 | M35: =IF(OR(J35="",H35=""),"",(C$35/D$35)*H35/360) -> 106.8093 | N35: =M35 -> 106.8093 | O35: =IF(J35="","",L35-M35) -> 967.2507
C36: Idrosanitaria Piave - Italie | E36: Bureautique | J36: =IF(J35="","",IF(J35+1>D$35+1,"",J35+1)) -> 2 | K36: =IF(J36="","",K35+1) -> 2023 | L36: =IF(J36="","",L35-M35) -> 967.2507 | M36: =IF(J36="","",IF(J36=D$35+1,(C$35/D$35)*(I$35/360),C$35/D$7)) -> 214.812 | N36: =IF(J36="","",N35+M36) -> 321.6213 | O36: =IF(J36="","",L36-M36) -> 752.4387
J37: =IF(J36="","",IF(J36+1>D$35+1,"",J36+1)) -> 3 | K37: =IF(J37="","",K36+1) -> 2024 | L37: =IF(J37="","",L36-M36) -> 752.4387 | M37: =IF(J37="","",IF(J37=D$35+1,(C$35/D$35)*(I$35/360),C$35/D$7)) -> 214.812 | N37: =IF(J37="","",N36+M37) -> 536.4333 | O37: =IF(J37="","",L37-M37) -> 537.6267
J38: =IF(J37="","",IF(J37+1>D$35+1,"",J37+1)) -> 4 | K38: =IF(J38="","",K37+1) -> 2025 | L38: =IF(J38="","",L37-M37) -> 537.6267 | M38: =IF(J38="","",IF(J38=D$35+1,(C$35/D$35)*(I$35/360),C$35/D$7)) -> 214.812 | N38: =IF(J38="","",N37+M38) -> 751.2453 | O38: =IF(J38="","",L38-M38) -> 322.8147
J39: =IF(J38="","",IF(J38+1>D$35+1,"",J38+1)) -> 5 | K39: =IF(J39="","",K38+1) -> 2026 | L39: =IF(J39="","",L38-M38) -> 322.8147 | M39: =IF(J39="","",IF(J39=D$35+1,(C$35/D$35)*(I$35/360),C$35/D$7)) -> 214.812 | N39: =IF(J39="","",N38+M39) -> 966.0573 | O39: =IF(J39="","",L39-M39) -> 108.0027
J40: =IF(J39="","",IF(J39+1>D$35+1,"",J39+1)) -> 6 | K40: =IF(J40="","",K39+1) -> 2027 | L40: =IF(J40="","",L39-M39) -> 108.0027 | M40: =IF(J40="","",IF(J40=D$35+1,(C$35/D$35)*(I$35/360),C$35/D$7)) -> 108.0027 | N40: =IF(J40="","",N39+M40) -> 1074.06 | O40: =IF(J40="","",L40-M40) -> -7.1054274e-14
B42: =B35+1 -> 6 | C42: 3805.13 | D42: 5 | E42: 45839 | F42: 45658 | G42: =YEAR(F42) -> 2025 | H42: 180 | I42: 180 | J42: =IF(OR(D42="",C42="",H42=""),"",1) -> 1 | K42: =IF(G42="","",G42) -> 2025 | L42: =IF(C42="","",C42) -> 3805.13 | M42: =IF(OR(J42="",H42=""),"",(C$42/D$42)*H42/360) -> 380.513 | N42: =M42 -> 380.513 | O42: =IF(J42="","",L42-M42) -> 3424.617
C43: Hornbach - Luxembourg | J43: =IF(J42="","",IF(J42+1>D$42+1,"",J42+1)) -> 2 | K43: =IF(J43="","",K42+1) -> 2026 | L43: =IF(J43="","",L42-M42) -> 3424.617 | M43: =IF(J43="","",IF(J43=D$42+1,(C$42/D$42)*(I$42/360),C$42/D$42)) -> 761.026 | N43: =IF(J43="","",N42+M43) -> 1141.539 | O43: =IF(J43="","",L43-M43) -> 2663.591
J44: =IF(J43="","",IF(J43+1>D$42+1,"",J43+1)) -> 3 | K44: =IF(J44="","",K43+1) -> 2027 | L44: =IF(J44="","",L43-M43) -> 2663.591 | M44: =IF(J44="","",IF(J44=D$42+1,(C$42/D$42)*(I$42/360),C$42/D$42)) -> 761.026 | N44: =IF(J44="","",N43+M44) -> 1902.565 | O44: =IF(J44="","",L44-M44) -> 1902.565
J45: =IF(J44="","",IF(J44+1>D$42+1,"",J44+1)) -> 4 | K45: =IF(J45="","",K44+1) -> 2028 | L45: =IF(J45="","",L44-M44) -> 1902.565 | M45: =IF(J45="","",IF(J45=D$42+1,(C$42/D$42)*(I$42/360),C$42/D$42)) -> 761.026 | N45: =IF(J45="","",N44+M45) -> 2663.591 | O45: =IF(J45="","",L45-M45) -> 1141.539
J46: =IF(J45="","",IF(J45+1>D$42+1,"",J45+1)) -> 5 | K46: =IF(J46="","",K45+1) -> 2029 | L46: =IF(J46="","",L45-M45) -> 1141.539 | M46: =IF(J46="","",IF(J46=D$42+1,(C$42/D$42)*(I$42/360),C$42/D$42)) -> 761.026 | N46: =IF(J46="","",N45+M46) -> 3424.617 | O46: =IF(J46="","",L46-M46) -> 380.513
J47: =IF(J46="","",IF(J46+1>D$42+1,"",J46+1)) -> 6 | K47: =IF(J47="","",K46+1) -> 2030 | L47: =IF(J47="","",L46-M46) -> 380.513 | M47: =IF(J47="","",IF(J47=D$42+1,(C$42/D$42)*(I$42/360),C$42/D$42)) -> 380.513 | N47: =IF(J47="","",N46+M47) -> 3805.13 | O47: =IF(J47="","",L47-M47) -> 1.1368684e-13
B49: =B42+1 -> 7 | G49: =YEAR(F49) -> 1900 | H49: =IF(OR(E49="",F49=""),"",(360-(E49-F49))) | I49: =IF(OR(E49="",F49=""),"",360-H49) | J49: =IF(OR(D49="",C49="",H49=""),"",1) | K49: =IF(G49="","",G49) -> 1900 | L49: =IF(C49="","",C49) | M49: =IF(OR(J49="",H49=""),"",(C$49/D$49)*H49/360) | N49: =M49 | O49: =IF(J49="","",L49-M49)
J50: =IF(J49="","",IF(J49+1>D$49+1,"",J49+1)) | K50: =IF(J50="","",K49+1) | L50: =IF(J50="","",L49-M49) | M50: =IF(J50="","",IF(J50=D$49+1,(C$49/D$49)*(I$49/360),C$49/D$49)) | N50: =IF(J50="","",N49+M50) | O50: =IF(J50="","",L50-M50)
J51: =IF(J50="","",IF(J50+1>D$49+1,"",J50+1)) | K51: =IF(J51="","",K50+1) | L51: =IF(J51="","",L50-M50) | M51: =IF(J51="","",IF(J51=D$49+1,(C$49/D$49)*(I$49/360),C$49/D$49)) | N51: =IF(J51="","",N50+M51) | O51: =IF(J51="","",L51-M51)
J52: =IF(J51="","",IF(J51+1>D$49+1,"",J51+1)) | K52: =IF(J52="","",K51+1) | L52: =IF(J52="","",L51-M51) | M52: =IF(J52="","",IF(J52=D$49+1,(C$49/D$49)*(I$49/360),C$49/D$49)) | N52: =IF(J52="","",N51+M52) | O52: =IF(J52="","",L52-M52)
J53: =IF(J52="","",IF(J52+1>D$49+1,"",J52+1)) | K53: =IF(J53="","",K52+1) | L53: =IF(J53="","",L52-M52) | M53: =IF(J53="","",IF(J53=D$49+1,(C$49/D$49)*(I$49/360),C$49/D$49)) | N53: =IF(J53="","",N52+M53) | O53: =IF(J53="","",L53-M53)
J54: =IF(J53="","",IF(J53+1>D$49+1,"",J53+1)) | K54: =IF(J54="","",K53+1) | L54: =IF(J54="","",L53-M53) | M54: =IF(J54="","",IF(J54=D$49+1,(C$49/D$49)*(I$49/360),C$49/D$49)) | N54: =IF(J54="","",N53+M54) | O54: =IF(J54="","",L54-M54)
B56: =B49+1 -> 8 | G56: =YEAR(F56) -> 1900 | H56: =IF(OR(E56="",F56=""),"",(360-(E56-F56))) | I56: =IF(OR(E56="",F56=""),"",360-H56) | J56: =IF(OR(D56="",C56="",H56=""),"",1) | K56: =IF(G56="","",G56) -> 1900 | L56: =IF(C56="","",C56) | M56: =IF(OR(J56="",H56=""),"",(C$56/D$56)*H56/360) | N56: =M56 | O56: =IF(J56="","",L56-M56)
J57: =IF(J56="","",IF(J56+1>D$56+1,"",J56+1)) | K57: =IF(J57="","",K56+1) | L57: =IF(J57="","",L56-M56) | M57: =IF(J57="","",IF(J57=D$56+1,(C$56/D$56)*(I$56/360),C$56/D$56)) | N57: =IF(J57="","",N56+M57) | O57: =IF(J57="","",L57-M57)
J58: =IF(J57="","",IF(J57+1>D$56+1,"",J57+1)) | K58: =IF(J58="","",K57+1) | L58: =IF(J58="","",L57-M57) | M58: =IF(J58="","",IF(J58=D$56+1,(C$56/D$56)*(I$56/360),C$56/D$56)) | N58: =IF(J58="","",N57+M58) | O58: =IF(J58="","",L58-M58)
J59: =IF(J58="","",IF(J58+1>D$56+1,"",J58+1)) | K59: =IF(J59="","",K58+1) | L59: =IF(J59="","",L58-M58) | M59: =IF(J59="","",IF(J59=D$56+1,(C$56/D$56)*(I$56/360),C$56/D$56)) | N59: =IF(J59="","",N58+M59) | O59: =IF(J59="","",L59-M59)
J60: =IF(J59="","",IF(J59+1>D$56+1,"",J59+1)) | K60: =IF(J60="","",K59+1) | L60: =IF(J60="","",L59-M59) | M60: =IF(J60="","",IF(J60=D$56+1,(C$56/D$56)*(I$56/360),C$56/D$56)) | N60: =IF(J60="","",N59+M60) | O60: =IF(J60="","",L60-M60)
J61: =IF(J60="","",IF(J60+1>D$56+1,"",J60+1)) | K61: =IF(J61="","",K60+1) | L61: =IF(J61="","",L60-M60) | M61: =IF(J61="","",IF(J61=D$56+1,(C$56/D$56)*(I$56/360),C$56/D$56)) | N61: =IF(J61="","",N60+M61) | O61: =IF(J61="","",L61-M61)

Sheet AMM A,B,C
B2: NEW LIFE Sàrl - Luxembourg | G2: 2025 | I2: TOTAUX
B4: 21 - IMMOBILISATIONS INCORPORELLES | I4: 21 - IMMOBILISATIONS INCORPORELLES
B5: 211 - FRAIS DE DEVELOPPEMENT
B6: Année | C6: Valeur comptable début d'exercise | D6: Annuité d'amortissement | E6: Amortissements cumulés | F6: Valeur nette comptable en fin d'exercice | G6: Valeur nette comptable en fin d'exercice | I6: Année | J6: Valeur comptable début d'exercise | K6: Annuité d'amortissement | L6: Amortissements cumulés | M6: Valeur nette comptable en fin d'exercice
B7: ='AMM A'!Q7 -> 2022 | C7: ='AMM A'!R7 -> 0 | D7: ='AMM A'!S7 -> 0 | E7: ='AMM A'!T7 -> 0 | F7: =SUMIF($I$21:$I$64,B7,$M$21:$M$64) -> 23191.443 | G7: ='AMM A'!U7 -> 0 | I7: 2022 | J7: =C7 -> 0 | K7: =D7 -> 0 | L7: =E7 -> 0 | M7: =G7 -> 0
B8: ='AMM A'!Q8 -> 2023 | C8: ='AMM A'!R8 -> 4391.65 | D8: ='AMM A'!S8 -> 195.97162 | E8: ='AMM A'!T8 -> 195.97162 | F8: =SUMIF($I$21:$I$64,B8,$M$21:$M$64) -> 40129.819 | G8: ='AMM A'!U8 -> 4195.6784 | I8: 2023 | J8: =C8 -> 4391.65 | K8: =D8 -> 195.97162 | L8: =E8 -> 195.97162 | M8: =G8 -> 4195.6784
B9: ='AMM A'!Q9 -> 2024 | C9: ='AMM A'!R9 -> 7198.9384 | D9: ='AMM A'!S9 -> 2161.8632 | E9: ='AMM A'!T9 -> 2357.8348 | F9: =SUMIF($I$21:$I$64,B9,$M$21:$M$64) -> 30522.472 | G9: ='AMM A'!U9 -> 5037.0752 | I9: 2024 | J9: =C9 -> 7198.9384 | K9: =D9 -> 2161.8632 | L9: =E9 -> 2357.8348 | M9: =G9 -> 5037.0752
B10: ='AMM A'!Q10 -> 2025 | C10: ='AMM A'!R10 -> 5037.0752 | D10: ='AMM A'!S10 -> 2464.97 | E10: ='AMM A'!T10 -> 4822.8048 | F10: =SUMIF($I$21:$I$64,B10,$M$21:$M$64) -> 24457.992 | G10: ='AMM A'!U10 -> 2572.1052 | I10: 2025 | J10: =C10 -> 5037.0752 | K10: =D10 -> 2464.97 | L10: =E10 -> 4822.8048 | M10: =G10 -> 2572.1052
B11: ='AMM A'!Q11 -> 2026 | C11: ='AMM A'!R11 -> 2572.1052 | D11: ='AMM A'!S11 -> 2268.9984 | E11: ='AMM A'!T11 -> 7091.8032 | F11: =SUMIF($I$21:$I$64,B11,$M$21:$M$64) -> 67894.659 | G11: ='AMM A'!U11 -> 303.1068 | I11: 2026 | J11: =C11 -> 2572.1052 | K11: =D11 -> 2268.9984 | L11: =E11 -> 7091.8032 | M11: =G11 -> 303.1068
B12: ='AMM A'!Q12 -> 2027 | C12: ='AMM A'!R12 -> 303.1068 | D12: ='AMM A'!S12 -> 303.1068 | E12: ='AMM A'!T12 -> 3003.26 | F12: =SUMIF($I$21:$I$64,B12,$M$21:$M$64) -> 47910.659 | G12: ='AMM A'!U12 -> 1.7053026e-13 | I12: 2027 | J12: =C12 -> 303.1068 | K12: =D12 -> 303.1068 | L12: =E12 -> 3003.26 | M12: =G12 -> 1.7053026e-13
B13: ='AMM A'!Q13 -> 2028 | C13: ='AMM A'!R13 -> 0 | D13: ='AMM A'!S13 -> 0 | E13: ='AMM A'!T13 -> 0 | F13: =SUMIF($I$21:$I$64,B13,$M$21:$M$64) -> 32817.675 | G13: ='AMM A'!U13 -> 0 | I13: 2028 | J13: =C13 -> 0 | K13: =D13 -> 0 | L13: =E13 -> 0 | M13: =G13 -> 0
B14: ='AMM A'!Q14 -> 2029 | C14: ='AMM A'!R14 -> 0 | D14: ='AMM A'!S14 -> 0 | E14: ='AMM A'!T14 -> 0 | F14: =SUMIF($I$21:$I$64,B14,$M$21:$M$64) -> 17724.691 | G14: ='AMM A'!U14 -> 0 | I14: 2029 | J14: =C14 -> 0 | K14: =D14 -> 0 | L14: =E14 -> 0 | M14: =G14 -> 0
B15: ='AMM A'!Q15 -> 2030 | C15: ='AMM A'!R15 -> 0 | D15: ='AMM A'!S15 -> 0 | E15: ='AMM A'!T15 -> 0 | F15: =SUMIF($I$21:$I$64,B15,$M$21:$M$64) -> 3392.733 | G15: ='AMM A'!U15 -> 0 | I15: 2030 | J15: =C15 -> 0 | K15: =D15 -> 0 | L15: =E15 -> 0 | M15: =G15 -> 0
B17: 22 - IMMOBILISATIONS CORPORELLES | I17: 22 - IMMOBILISATIONS CORPORELLES
B18: 2232 - VEHICULES DE TRANSPORT
B19: Année | C19: Valeur comptable début d'exercise | D19: Annuité d'amortissement | E19: Amortissements cumulés | F19: Valeur nette comptable en fin d'exercice | G19: Valeur nette comptable en fin d'exercice | I19: Année | J19: Valeur comptable début d'exercise | K19: Annuité d'amortissement | L19: Amortissements cumulés | M19: Valeur nette comptable en fin d'exercice
B20: ='AMM B'!Q7 -> 2022 | C20: ='AMM B'!R7 -> 17562.82 | D20: ='AMM B'!S7 -> 1756.282 | E20: ='AMM B'!T7 -> 1756.282 | F20: =SUMIF($I$21:$I$64,B20,$M$21:$M$64) -> 23191.443 | G20: ='AMM B'!U7 -> 15806.538 | I20: 2022 | J20: =C33+C20 -> 26121.86 | K20: =D33+D20 -> 2930.4175 | L20: =E33+E20 -> 2930.4175 | M20: =G33+G20 -> 23191.443
B21: ='AMM B'!Q8 -> 2023 | C21: ='AMM B'!R8 -> 15806.538 | D21: ='AMM B'!S8 -> 3512.564 | E21: ='AMM B'!T8 -> 5268.846 | F21: =SUMIF($I$21:$I$64,B21,$M$21:$M$64) -> 40129.819 | G21: ='AMM B'!U8 -> 12293.974 | I21: 2023 | J21: =C34+C21 -> 23191.443 | K21: =D34+D21 -> 5224.372 | L21: =E34+E21 -> 8154.7895 | M21: =G34+G21 -> 17967.071
B22: ='AMM B'!Q9 -> 2024 | C22: ='AMM B'!R9 -> 12293.974 | D22: ='AMM B'!S9 -> 3512.564 | E22: ='AMM B'!T9 -> 8781.41 | F22: =SUMIF($I$21:$I$64,B22,$M$21:$M$64) -> 30522.472 | G22: ='AMM B'!U9 -> 8781.41 | I22: 2024 | J22: =C35+C22 -> 17967.071 | K22: =D35+D22 -> 5224.372 | L22: =E35+E22 -> 13379.161 | M22: =G35+G22 -> 12742.699
B23: ='AMM B'!Q10 -> 2025 | C23: ='AMM B'!R10 -> 8781.41 | D23: ='AMM B'!S10 -> 3512.564 | E23: ='AMM B'!T10 -> 12293.974 | F23: =SUMIF($I$21:$I$64,B23,$M$21:$M$64) -> 24457.992 | G23: ='AMM B'!U10 -> 5268.846 | I23: 2025 | J23: =C36+C23 -> 16547.829 | K23: =D36+D23 -> 5604.885 | L23: =E36+E23 -> 18984.046 | M23: =G36+G23 -> 10942.944
B24: ='AMM B'!Q11 -> 2026 | C24: ='AMM B'!R11 -> 39196.176 | D24: ='AMM B'!S11 -> 8601.6635 | E24: ='AMM B'!T11 -> 20895.638 | F24: =SUMIF($I$21:$I$64,B24,$M$21:$M$64) -> 67894.659 | G24: ='AMM B'!U11 -> 30594.513 | I24: 2026 | J24: =C37+C24 -> 44870.274 | K24: =D37+D24 -> 11074.498 | L24: =E37+E24 -> 30058.544 | M24: =G37+G24 -> 33795.776
B25: ='AMM B'!Q12 -> 2027 | C25: ='AMM B'!R12 -> 30594.513 | D25: ='AMM B'!S12 -> 8541.748 | E25: ='AMM B'!T12 -> 29437.386 | F25: =SUMIF($I$21:$I$64,B25,$M$21:$M$64) -> 47910.659 | G25: ='AMM B'!U12 -> 22052.765 | I25: 2027 | J25: =C38+C25 -> 33795.776 | K25: =D38+D25 -> 9840.4465 | L25: =E38+E25 -> 39898.99 | M25: =G38+G25 -> 23955.329
B26: ='AMM B'!Q13 -> 2028 | C26: ='AMM B'!R13 -> 22052.765 | D26: ='AMM B'!S13 -> 6785.466 | E26: ='AMM B'!T13 -> 18660.032 | F26: =SUMIF($I$21:$I$64,B26,$M$21:$M$64) -> 32817.675 | G26: ='AMM B'!U13 -> 15267.299 | I26: 2028 | J26: =C39+C26 -> 23955.329 | K26: =D39+D26 -> 7546.492 | L26: =E39+E26 -> 21323.623 | M26: =G39+G26 -> 16408.838
B27: ='AMM B'!Q14 -> 2029 | C27: ='AMM B'!R14 -> 15267.299 | D27: ='AMM B'!S14 -> 6785.466 | E27: ='AMM B'!T14 -> 25445.498 | F27: =SUMIF($I$21:$I$64,B27,$M$21:$M$64) -> 17724.691 | G27: ='AMM B'!U14 -> 8481.8325 | I27: 2029 | J27: =C40+C27 -> 16408.838 | K27: =D40+D27 -> 7546.492 | L27: =E40+E27 -> 28870.115 | M27: =G40+G27 -> 8862.3455
B28: ='AMM B'!Q15 -> 2030 | C28: ='AMM B'!R15 -> 8481.8325 | D28: ='AMM B'!S15 -> 6785.466 | E28: ='AMM B'!T15 -> 32230.964 | F28: =SUMIF($I$21:$I$64,B28,$M$21:$M$64) -> 3392.733 | G28: ='AMM B'!U15 -> 1696.3665 | I28: 2030 | J28: =C41+C28 -> 8862.3455 | K28: =D41+D28 -> 7165.979 | L28: =E41+E28 -> 36036.094 | M28: =G41+G28 -> 1696.3665
B30: 22 - IMMOBILISATIONS CORPORELLES | I30: TOTAL IMMOBILISATIONS
B31: 2234 - MOBILIER
B32: Année | C32: Valeur comptable début d'exercise | D32: Annuité d'amortissement | E32: Amortissements cumulés | F32: Valeur nette comptable en fin d'exercice | G32: Valeur nette comptable en fin d'exercice | I32: Année | J32: Valeur comptable début d'exercise | K32: Annuité d'amortissement | L32: Amortissements cumulés | M32: Valeur nette comptable en fin d'exercice
B33: ='AMM C'!Q7 -> 2022 | C33: ='AMM C'!R7 -> 8559.04 | D33: ='AMM C'!S7 -> 1174.1355 | E33: ='AMM C'!T7 -> 1174.1355 | F33: =SUMIF($I$21:$I$64,B33,$M$21:$M$64) -> 23191.443 | G33: ='AMM C'!U7 -> 7384.9045 | I33: 2022 | J33: =J7+J20 -> 26121.86 | K33: =K7+K20 -> 2930.4175 | L33: =L7+L20 -> 2930.4175 | M33: =M7+M20 -> 23191.443
B34: ='AMM C'!Q8 -> 2023 | C34: ='AMM C'!R8 -> 7384.9045 | D34: ='AMM C'!S8 -> 1711.808 | E34: ='AMM C'!T8 -> 2885.9435 | F34: =SUMIF($I$21:$I$64,B34,$M$21:$M$64) -> 40129.819 | G34: ='AMM C'!U8 -> 5673.0965 | I34: 2023 | J34: =J8+J21 -> 27583.093 | K34: =K8+K21 -> 5420.3436 | L34: =L8+L21 -> 8350.7611 | M34: =M8+M21 -> 22162.749
B35: ='AMM C'!Q9 -> 2024 | C35: ='AMM C'!R9 -> 5673.0965 | D35: ='AMM C'!S9 -> 1711.808 | E35: ='AMM C'!T9 -> 4597.7515 | F35: =SUMIF($I$21:$I$64,B35,$M$21:$M$64) -> 30522.472 | G35: ='AMM C'!U9 -> 3961.2885 | I35: 2024 | J35: =J9+J22 -> 25166.009 | K35: =K9+K22 -> 7386.2352 | L35: =L9+L22 -> 15736.996 | M35: =M9+M22 -> 17779.774
B36: ='AMM C'!Q10 -> 2025 | C36: ='AMM C'!R10 -> 7766.4185 | D36: ='AMM C'!S10 -> 2092.321 | E36: ='AMM C'!T10 -> 6690.0725 | F36: =SUMIF($I$21:$I$64,B36,$M$21:$M$64) -> 24457.992 | G36: ='AMM C'!U10 -> 5674.0975 | I36: 2025 | J36: =J10+J23 -> 21584.904 | K36: =K10+K23 -> 8069.855 | L36: =L10+L23 -> 23806.851 | M36: =M10+M23 -> 13515.049
B37: ='AMM C'!Q11 -> 2026 | C37: ='AMM C'!R11 -> 5674.0975 | D37: ='AMM C'!S11 -> 2472.834 | E37: ='AMM C'!T11 -> 9162.9065 | F37: =SUMIF($I$21:$I$64,B37,$M$21:$M$64) -> 67894.659 | G37: ='AMM C'!U11 -> 3201.2635 | I37: 2026 | J37: =J11+J24 -> 47442.379 | K37: =K11+K24 -> 13343.496 | L37: =L11+L24 -> 37150.347 | M37: =M11+M24 -> 34098.883
B38: ='AMM C'!Q12 -> 2027 | C38: ='AMM C'!R12 -> 3201.2635 | D38: ='AMM C'!S12 -> 1298.6985 | E38: ='AMM C'!T12 -> 10461.605 | F38: =SUMIF($I$21:$I$64,B38,$M$21:$M$64) -> 47910.659 | G38: ='AMM C'!U12 -> 1902.565 | I38: 2027 | J38: =J12+J25 -> 34098.883 | K38: =K12+K25 -> 10143.553 | L38: =L12+L25 -> 42902.251 | M38: =M12+M25 -> 23955.329
B39: ='AMM C'!Q13 -> 2028 | C39: ='AMM C'!R13 -> 1902.565 | D39: ='AMM C'!S13 -> 761.026 | E39: ='AMM C'!T13 -> 2663.591 | F39: =SUMIF($I$21:$I$64,B39,$M$21:$M$64) -> 32817.675 | G39: ='AMM C'!U13 -> 1141.539 | I39: 2028 | J39: =J13+J26 -> 23955.329 | K39: =K13+K26 -> 7546.492 | L39: =L13+L26 -> 21323.623 | M39: =M13+M26 -> 16408.838
B40: ='AMM C'!Q14 -> 2029 | C40: ='AMM C'!R14 -> 1141.539 | D40: ='AMM C'!S14 -> 761.026 | E40: ='AMM C'!T14 -> 3424.617 | F40: =SUMIF($I$21:$I$64,B40,$M$21:$M$64) -> 17724.691 | G40: ='AMM C'!U14 -> 380.513 | I40: 2029 | J40: =J14+J27 -> 16408.838 | K40: =K14+K27 -> 7546.492 | L40: =L14+L27 -> 28870.115 | M40: =M14+M27 -> 8862.3455
B41: ='AMM C'!Q15 -> 2030 | C41: ='AMM C'!R15 -> 380.513 | D41: ='AMM C'!S15 -> 380.513 | E41: ='AMM C'!T15 -> 3805.13 | F41: =SUMIF($I$21:$I$64,B41,$M$21:$M$64) -> 3392.733 | G41: ='AMM C'!U15 -> 1.1368684e-13 | I41: 2030 | J41: =J15+J28 -> 8862.3455 | K41: =K15+K28 -> 7165.979 | L41: =L15+L28 -> 36036.094 | M41: =M15+M28 -> 1696.3665

Sheet Amortissements
B2: 21 - IMMOBILISATIONS INCORPORELLES
B3: 211 - FRAIS DE DEVELOPPEMENT | G3: SOFTWARE | I3: Prix d'acquisition hors TVA | K3: TVA | L3: Prix d'acquisition TTC
B4: 45204 | C4: =IF(B4="","",YEAR(B4)) -> 2023 | D4: Bureautique | E4: Paksi Company | G4: Software | H4: INTR - INV | I4: -1007.2 | J4: 0 | K4: 0 | L4: =I4+K4 -> -1007.2 | M4: 04/2023 | O4: RIMBORSO | P4: 17-2023 | Q4: COSTI
B5: 45204 | C5: =IF(B5="","",YEAR(B5)) -> 2023 | D5: Bureautique | E5: Paksi Company | G5: Software | H5: INTR - INV | I5: -1200.77 | J5: 0 | K5: 0 | L5: =I5+K5 -> -1200.77 | M5: 04/2023 | O5: RIMBORSO | P5: 17-2023 | Q5: COSTI
B6: 45274 | C6: =IF(B6="","",YEAR(B6)) -> 2023 | D6: Bureautique | E6: Paksi Company | G6: Software | H6: INTR - INV | I6: -2183.68 | J6: 0 | K6: 0 | L6: =I6+K6 -> -2183.68 | M6: 04/2023 | O6: RIMBORSO | P6: 17-2023 | Q6: COSTI
B7: 45401 | C7: =IF(B7="","",YEAR(B7)) -> 2024 | D7: Bureautique | E7: Paksi Company | G7: Software | H7: INTR - INV | I7: -3003.26 | J7: 0 | K7: 0 | L7: =I7+K7 -> -3003.26 | M7: 02/2024 | O7: RIMBORSO | P7: 19-2024 | Q7: COSTI
I8: =SUM(I4:I7) -> -7394.91 | L8: =SUM(L4:L7) -> -7394.91
B9: 22 - IMMOBILISATIONS CORPORELLES
B10: 2232 - VEHICULES DE TRANSPORT | G10: VEHICULES MOTEUR | I10: Prix d'acquisition hors TVA | K10: TVA | L10: Prix d'acquisition TTC
B11: 44743 | C11: =IF(B11="","",YEAR(B11)) -> 2022 | D11: Bureautique | E11: Car Avenue - Peugeot | G11: Voitures | H11: LUX - INV | I11: -25512.82 | J11: 0.17 | K11: =I11*J11 -> -4337.1794 | L11: =I11+K11 -> -29849.999 | O11: FATTURE | P11: FATTURE | Q11: COSTI
B12: 44743 | C12: =IF(B12="","",YEAR(B12)) -> 2022 | D12: Bureautique | E12: Car Avenue - Peugeot | G12: Voitures | H12: LUX - INV | I12: -50 | J12: 0 | K12: =I12*J12 -> 0 | L12: =I12+K12 -> -50 | O12: FATTURE | P12: FATTURE | Q12: COSTI
B13: 45041 | C13: =IF(B13="","",YEAR(B13)) -> 2023 | D13: Bureautique | E13: Administration | G13: Prime d'état | H13: LUX - INV | I13: 8000 | J13: 0 | K13: =I13*J13 -> 0 | L13: =I13+K13 -> 8000 | O13: FATTURE | P13: FATTURE | Q13: COSTI
B14: 46122 | C14: =IF(B14="","",YEAR(B14)) -> 2026 | D14: Bureautique | E14: Garage Pauly-Losch | G14: Voitures | H14: LUX - INV | I14: -33927.23 | J14: 0.17 | K14: =I14*J14 -> -5767.6291 | L14: =I14+K14 -> -39694.859 | O14: FATTURE | P14: FATTURE | Q14: COSTI
I15: =SUBTOTAL(9,I11:I14) -> -51490.05 | L15: =SUM(L11:L14) -> -61594.859
B16: 22 - IMMOBILISATIONS CORPORELLES
B17: 2234 - MOBILIER | G17: MEUBLES | I17: Prix d'acquisition hors TVA | K17: TVA | L17: Prix d'acquisition TTC
B18: 44608 | C18: =IF(B18="","",YEAR(B18)) -> 2022 | D18: Bureautique | E18: Idrosanitaria Piave - Italie | G18: Meubles | H18: INTR - INV | I18: -1520 | J18: 0 | K18: 0 | L18: -1520 | O18: FATTURE | P18: FATTURE | Q18: COSTI
B19: 44743 | C19: =IF(B19="","",YEAR(B19)) -> 2022 | D19: Bureautique | E19: Idrosanitaria Piave - Italie | G19: Meubles | H19: INTR - INV | I19: -1074.06 | J19: 0 | K19: 0 | L19: -1074.06 | O19: FATTURE | P19: FATTURE | Q19: COSTI
B20: 44681 | C20: =IF(B20="","",YEAR(B20)) -> 2022 | D20: Bureautique | E20: Idrosanitaria Piave - Italie | G20: Meubles | H20: INTR - INV | I20: -3541.67 | J20: 0 | K20: 0 | L20: -3541.67 | M20: 03/2022 | O20: RIMBORSO | P20: 11-2022 | Q20: COSTI
B21: 44664 | C21: =IF(B21="","",YEAR(B21)) -> 2022 | D21: Bureautique | E21: SME S.p.A. | G21: Meubles | H21: INTR - INV | I21: -1020 | J21: 0 | K21: 0 | L21: -1020 | M21: 03/2022 | O21: RIMBORSO | P21: 11-2022 | Q21: COSTI
B22: 44691 | C22: =IF(B22="","",YEAR(B22)) -> 2022 | D22: Bureautique | E22: IKEA Arlon | G22: Meubles | H22: INTR - INV | I22: -1403.31 | J22: 0 | K22: 0 | L22: -1403.31 | M22: 03/2022 | O22: RIMBORSO | P22: 11-2022 | Q22: COSTI
B23: 45839 | C23: =IF(B23="","",YEAR(B23)) -> 2025 | D23: Bureautique | E23: Hornbach - Luxembourg | G23: Meubles | H23: INTR - INV | I23: -769.23 | J23: 0.17 | K23: =I23*J23 -> -130.7691 | L23: =I23+K23 -> -899.9991 | M23: 03/2025 | O23: RIMBORSO | P23: 24-2025 | Q23: COSTI
B24: 45857 | C24: =IF(B24="","",YEAR(B24)) -> 2025 | D24: Bureautique | E24: Hornbach - Luxembourg | G24: Meubles | H24: INTR - INV | I24: -3035.9 | J24: 0.17 | K24: =I24*J24 -> -516.103 | L24: =I24+K24 -> -3552.003 | M24: 03/2025 | O24: RIMBORSO | P24: 24-2025 | Q24: COSTI
I25: =SUM(I18:I24) -> -12364.17 | L25: =SUBTOTAL(9,L18:L24) -> -13011.042
D27: AMORTISSEMENT SOFTWARE | H27: AMORTISSEMENT VEHICULES | L27: AMORTISSEMENT MEUBLES | P27: AMORTISSEMENT TOTAL
D28: Annuité amortissement | E28: Valeur nette comptable en fin d'exercice | H28: Annuité amortissement | I28: Valeur nette comptable en fin d'exercice | L28: Annuité amortissement | M28: Valeur nette comptable en fin d'exercice | P28: Annuité amortissement | Q28: Valeur nette comptable en fin d'exercice
E29: =-I8 -> 7394.91 | I29: =-I15 -> 51490.05 | M29: =-I25 -> 12364.17 | Q29: =M29+I29+E29 -> 71249.13
C30: 2022 | D30: =-'AMM A,B,C'!D7 -> 0 | E30: 0 | G30: 2022 | H30: =-'AMM A,B,C'!D20 -> -1756.282 | I30: =I29+H30 -> 49733.768 | K30: 2022 | L30: =-'AMM A,B,C'!D33 -> -1174.1355 | M30: =M29+L30 -> 11190.035 | O30: 2022 | P30: =+L30+H30+D30 -> -2930.4175 | Q30: =Q29+P30 -> 68318.713
C31: 2023 | D31: =-'AMM A,B,C'!D8 -> -195.97162 | E31: =E29+D31 -> 7198.9384 | G31: 2023 | H31: =-'AMM A,B,C'!D21 -> -3512.564 | I31: =I30+H31 -> 46221.204 | K31: 2023 | L31: =-'AMM A,B,C'!D34 -> -1711.808 | M31: =M30+L31 -> 9478.2265 | O31: 2023 | P31: =+L31+H31+D31 -> -5420.3436 | Q31: =+M31+I31+E31 -> 62898.369
C32: 2024 | D32: =-'AMM A,B,C'!D9 -> -2161.8632 | E32: =E31+D32 -> 5037.0752 | G32: 2024 | H32: =-'AMM A,B,C'!D22 -> -3512.564 | I32: =I31+H32 -> 42708.64 | K32: 2024 | L32: =-'AMM A,B,C'!D35 -> -1711.808 | M32: =M31+L32 -> 7766.4185 | O32: 2024 | P32: =+L32+H32+D32 -> -7386.2352 | Q32: =+M32+I32+E32 -> 55512.134
C33: 2025 | D33: =-'AMM A,B,C'!D10 -> -2464.97 | E33: =E32+D33 -> 2572.1052 | G33: 2025 | H33: =-'AMM A,B,C'!D23 -> -3512.564 | I33: =I32+H33 -> 39196.076 | K33: 2025 | L33: =-'AMM A,B,C'!D36 -> -2092.321 | M33: =M32+L33 -> 5674.0975 | O33: 2025 | P33: =+L33+H33+D33 -> -8069.855 | Q33: =+M33+I33+E33 -> 47442.279
C34: 2026 | D34: =-'AMM A,B,C'!D11 -> -2268.9984 | E34: =E33+D34 -> 303.1068 | G34: 2026 | H34: =-'AMM A,B,C'!D24 -> -8601.6635 | I34: =I33+H34 -> 30594.413 | K34: 2026 | L34: =-'AMM A,B,C'!D37 -> -2472.834 | M34: =M33+L34 -> 3201.2635 | O34: 2026 | P34: =+L34+H34+D34 -> -13343.496 | Q34: =+M34+I34+E34 -> 34098.783
C35: 2027 | D35: =-'AMM A,B,C'!D12 -> -303.1068 | E35: =E34+D35 -> 0 | G35: 2027 | H35: =-'AMM A,B,C'!D25 -> -8541.748 | I35: =I34+H35 -> 22052.665 | K35: 2027 | L35: =-'AMM A,B,C'!D38 -> -1298.6985 | M35: =M34+L35 -> 1902.565 | O35: 2027 | P35: =+L35+H35+D35 -> -10143.553 | Q35: =+M35+I35+E35 -> 23955.23
C36: 2028 | D36: =-'AMM A,B,C'!D13 -> 0 | E36: =E35+D36 -> 0 | G36: 2028 | H36: =-'AMM A,B,C'!D26 -> -6785.466 | I36: =I35+H36 -> 15267.199 | K36: 2028 | L36: =-'AMM A,B,C'!D39 -> -761.026 | M36: =M35+L36 -> 1141.539 | O36: 2028 | P36: =+L36+H36+D36 -> -7546.492 | Q36: =+M36+I36+E36 -> 16408.738
C37: 2029 | D37: =-'AMM A,B,C'!D14 -> 0 | E37: =E36+D37 -> 0 | G37: 2029 | H37: =-'AMM A,B,C'!D27 -> -6785.466 | I37: =I36+H37 -> 8481.7325 | K37: 2029 | L37: =-'AMM A,B,C'!D40 -> -761.026 | M37: =M36+L37 -> 380.513 | O37: 2029 | P37: =+L37+H37+D37 -> -7546.492 | Q37: =+M37+I37+E37 -> 8862.2455
C38: 2030 | D38: =-'AMM A,B,C'!D15 -> 0 | E38: =E37+D38 -> 0 | G38: 2030 | H38: =-'AMM A,B,C'!D28 -> -6785.466 | I38: =I37+H38 -> 1696.2665 | K38: 2030 | L38: =-'AMM A,B,C'!D41 -> -380.513 | M38: =M37+L38 -> -2.3874236e-12 | O38: 2030 | P38: =+L38+H38+D38 -> -7165.979 | Q38: =+M38+I38+E38 -> 1696.2665
D39: =SUBTOTAL(9,D30:D38) -> -7394.91 | H39: =SUBTOTAL(9,H30:H38) -> -49793.784 | L39: =SUM(L30:L38) -> -12364.17 | P39: =SUBTOTAL(9,P30:P38) -> -69552.863

Sheet 2026 Marius
B2: No fiscal : 1980 2403 189 | G2: TABLEAU D'AMORTISSEMENT : 2026
B3: nom : NEW LIFE Sàrl
A5: NR | B5: Désignation du bien | C5: Date | D5: Valeur | E5: Taux | F5: /12 | G5: Valeur | H5: Acquisitions | I5: Ventes | J5: Amortissements | K5: Valeur | L5: Bén/Perte
C6: d'acquisition | D6: à amortir | E6: % | G6: début | H6: de l'année | I6: de l'année | J6: de l'année | K6: fin | L6: s/ventes
B8: IMMOBILISE CORPOREL
B9: MEUBLES
A10: 1 | B10: Installation bureau | C10: 14.02.2022 | D10: 1520 | E10: 0.2 | F10: 12 | G10: ='2025 Marius'!K10 -> 341.16 | J10: =(D10*E10)*F10/12 -> 304 | K10: =G10-J10 -> 37.16
A11: 2 | B11: Installation bureau | C11: 13.04.2022 | D11: 1020 | E11: 0.2 | F11: 12 | G11: ='2025 Marius'!K11 -> 261.8 | J11: =(D11*E11)*F11/12 -> 204 | K11: =G11-J11 -> 57.8
A12: 3 | B12: Installation bureau | C12: 30.04.2022 | D12: 3541.67 | E12: 0.2 | F12: 12 | G12: ='2025 Marius'!K12 -> 942.486 | J12: =(D12*E12)*F12/12 -> 708.334 | K12: =G12-J12 -> 234.152
A13: 4 | B13: Installation bureau | C13: 10.05.2022 | D13: 1403.31 | E13: 0.2 | F13: 12 | G13: ='2025 Marius'!K13 -> 381.238 | J13: =(D13*E13)*F13/12 -> 280.662 | K13: =G13-J13 -> 100.576
A14: 5 | B14: Installation bureau | C14: 01.07.2022 | D14: 1074.06 | E14: 0.2 | F14: 12 | G14: ='2025 Marius'!K14 -> 322.798 | J14: =(D14*E14)*F14/12 -> 214.812 | K14: =G14-J14 -> 107.986
A15: 6 | B15: Installation bureau | C15: 1.07.2025 | D15: 769.23 | E15: 0.2 | F15: 12 | G15: ='2025 Marius'!K15 -> 692.307 | J15: =(D15*E15)*F15/12 -> 153.846 | K15: =G15-J15 -> 538.461
A16: 7 | B16: Installation bureau | C16: 19.07.2025 | D16: 3035.9 | E16: 0.2 | F16: 12 | G16: ='2025 Marius'!K16 -> 2732.31 | J16: =(D16*E16)*F16/12 -> 607.18 | K16: =G16-J16 -> 2125.13
J17: =SUM(J10:J16) -> 2472.834 | K17: =SUM(K10:K16) -> 3201.265
B18: VOITURES
A19: 8 | B19: Voiture Peugeot | C19: 01.07.2022 | D19: 17562.82 | E19: 0.2 | F19: 12 | G19: ='2025 Marius'!K19 -> 5268.856 | J19: =(D19*E19)*F19/12 -> 3512.564 | K19: =G19-J19 -> 1756.292
A20: 9 | B20: Voiture VW Tiguan | C20: 10.04.2026 | D20: 33927.23 | E20: 0.2 | F20: 9 | H20: =D20 -> 33927.23 | J20: =(D20*E20)*F20/12 -> 5089.0845 | K20: =H20-J20 -> 28838.146
J21: =SUM(J19:J20) -> 8601.6485 | K21: =SUM(K19:K20) -> 30594.438
B23: IMMOBILISE INCORPOREL
B24: SOFTWARE
A25: 10 | B25: Bureautique, Software | C25: 2023 | D25: 4391.65 | E25: 0.33333 | F25: 12 | G25: ='2025 Marius'!K24 -> 1267.9313 | J25: 1267.93 | K25: =G25-J25 -> 0.0013055
A26: 11 | B26: Bureautique, Software | C26: 2024 | D26: 3003.26 | E26: 0.33333 | F26: 12 | G26: ='2025 Marius'!K25 -> 1304.2033 | J26: =(D26*E26)*F26/12 -> 1001.0767 | K26: =G26-J26 -> 303.12669
J27: =SUM(J25:J26) -> 2269.0067 | K27: =SUM(K25:K26) -> 303.12799
D30: =SUM(D7:D29) -> 71249.13 | G30: =SUM(G8:G29) -> 13515.09 | H30: =SUM(H7:H29) -> 33927.23 | I30: =SUM(I7:I29) -> 0 | J30: =J17+J21+J27 -> 13343.489 | K30: =K17+K21+K27 -> 34098.83 | L30: =SUM(L7:L29) -> 0

Sheet 2025 Marius
B2: No fiscal : 1980 2403 189 | G2: TABLEAU D'AMORTISSEMENT : 2025
B3: nom : NEW LIFE Sàrl
A5: NR | B5: Désignation du bien | C5: Date | D5: Valeur | E5: Taux | F5: /12 | G5: Valeur | H5: Acquisitions | I5: Ventes | J5: Amortissements | K5: Valeur | L5: Bén/Perte
C6: d'acquisition | D6: à amortir | E6: % | G6: début | H6: de l'année | I6: de l'année | J6: de l'année | K6: fin | L6: s/ventes
B8: IMMOBILISE CORPOREL
A10: 1 | B10: Installation bureau | C10: 14.02.2022 | D10: 1520 | E10: 0.2 | F10: 12 | G10: ='2024 Marius'!K10 -> 645.16 | J10: =(D10*E10)*F10/12 -> 304 | K10: =G10-J10 -> 341.16
A11: 2 | B11: Installation bureau | C11: 13.04.2022 | D11: 1020 | E11: 0.2 | F11: 12 | G11: ='2024 Marius'!K11 -> 465.8 | J11: =(D11*E11)*F11/12 -> 204 | K11: =G11-J11 -> 261.8
A12: 3 | B12: Installation bureau | C12: 30.04.2022 | D12: 3541.67 | E12: 0.2 | F12: 12 | G12: ='2024 Marius'!K12 -> 1650.82 | J12: =(D12*E12)*F12/12 -> 708.334 | K12: =G12-J12 -> 942.486
A13: 4 | B13: Installation bureau | C13: 10.05.2022 | D13: 1403.31 | E13: 0.2 | F13: 12 | G13: ='2024 Marius'!K13 -> 661.9 | J13: =(D13*E13)*F13/12 -> 280.662 | K13: =G13-J13 -> 381.238
A14: 5 | B14: Installation bureau | C14: 01.07.2022 | D14: 1074.06 | E14: 0.2 | F14: 12 | G14: ='2024 Marius'!K14 -> 537.61 | J14: =(D14*E14)*F14/12 -> 214.812 | K14: =G14-J14 -> 322.798
A15: 6 | B15: Installation bureau | C15: 1.07.2025 | D15: 769.23 | E15: 0.2 | F15: 6 | H15: 769.23 | J15: =(D15*E15)*F15/12 -> 76.923 | K15: =H15-J15 -> 692.307
A16: 7 | B16: Installation bureau | C16: 19.07.2025 | D16: 3035.9 | E16: 0.2 | F16: 6 | H16: 3035.9 | J16: =(D16*E16)*F16/12 -> 303.59 | K16: =H16-J16 -> 2732.31
J17: =SUM(J10:J16) -> 2092.321 | K17: =SUM(K10:K16) -> 5674.099
A19: 8 | B19: Voiture Peugeot | C19: 01.07.2022 | D19: 17562.82 | E19: 0.2 | F19: 12 | G19: ='2024 Marius'!K16 -> 8781.42 | J19: =(D19*E19)*F19/12 -> 3512.564 | K19: =G19-J19 -> 5268.856
B22: IMMOBILISE INCORPOREL
A24: 9 | B24: Bureautique, Software | C24: 2023 | D24: 4391.65 | E24: 0.33333 | F24: 12 | G24: ='2024 Marius'!K24 -> 2731.8 | J24: =(D24*E24)*F24/12 -> 1463.8687 | K24: =G24-J24 -> 1267.9313
A25: 10 | B25: Bureautique, Software | C25: 2024 | D25: 3003.26 | E25: 0.33333 | F25: 12 | G25: ='2024 Marius'!K25 -> 2305.28 | J25: =(D25*E25)*F25/12 -> 1001.0767 | K25: =G25-J25 -> 1304.2033
J26: =SUM(J24:J25) -> 2464.9454 | K26: =SUM(K24:K25) -> 2572.1346
D29: =SUM(D7:D28) -> 37321.9 | G29: 17779.79 | H29: =SUM(H7:H28) -> 3805.13 | I29: =SUM(I7:I28) -> 0 | J29: =J17+J19+J26 -> 8069.8304 | K29: =K17+K19+K26 -> 13515.09 | L29: =SUM(L7:L28) -> 0

Sheet 2024 Marius
B2: No fiscal : 1980 2403 189 | G2: TABLEAU D'AMORTISSEMENT : 2024
B3: nom : NEW LIFE Sàrl
A5: NR | B5: Désignation du bien | C5: Date | D5: Valeur | E5: Taux | F5: /12 | G5: Valeur | H5: Acquisitions | I5: Ventes | J5: Amortissements | K5: Valeur | L5: Bén/Perte
C6: d'acquisition | D6: à amortir | E6: % | G6: début | H6: de l'année | I6: de l'année | J6: de l'année | K6: fin | L6: s/ventes
B8: IMMOBILISE CORPOREL
A10: 1 | B10: Installation bureau | C10: 14.02.2022 | D10: 1520 | E10: 0.2 | F10: 12 | G10: 949.16 | J10: 304 | K10: =G10-J10 -> 645.16
A11: 2 | B11: Installation bureau | C11: 13.04.2022 | D11: 1020 | E11: 0.2 | F11: 12 | G11: 669.8 | J11: 204 | K11: =G11-J11 -> 465.8
A12: 3 | B12: Installation bureau | C12: 30.04.2022 | D12: 3541.67 | E12: 0.2 | F12: 12 | G12: 2359.15 | J12: 708.33 | K12: =G12-J12 -> 1650.82
A13: 4 | B13: Installation bureau | C13: 10.05.2022 | D13: 1403.31 | E13: 0.2 | F13: 12 | G13: 942.56 | J13: 280.66 | K13: =G13-J13 -> 661.9
A14: 5 | B14: Installation bureau | C14: 01.07.2022 | D14: 1074.06 | E14: 0.2 | F14: 12 | G14: 752.43 | J14: 214.82 | K14: =G14-J14 -> 537.61
A16: 6 | B16: Voiture Peugeot | C16: 01.07.2022 | D16: 17562.82 | E16: 0.2 | F16: 12 | G16: 12293.98 | J16: 3512.56 | K16: =G16-J16 -> 8781.42
B22: IMMOBILISE INCORPOREL
A24: 7 | B24: Bureautique, Software | C24: 2023 | D24: 4391.65 | E24: 0.33333 | F24: 12 | G24: 4195.68 | J24: 1463.88 | K24: =G24-J24 -> 2731.8
A25: 8 | B25: Bureautique, Software | C25: 2024 | D25: 3003.26 | E25: 0.33333 | F25: 9 | H25: 3003.26 | J25: 697.98 | K25: =H25-J25 -> 2305.28
D29: =SUM(D7:D28) -> 33516.77 | G29: =SUM(G7:G28) -> 22162.76 | H29: =SUM(H7:H28) -> 3003.26 | I29: =SUM(I7:I28) -> 0 | J29: =SUM(J7:J28) -> 7386.23 | K29: =SUM(K7:K28) -> 17779.79 | L29: =SUM(L7:L28) -> 0
